{
"type": "FeatureCollection",
"crs": { "type": "name", "properties": { "name": "urn:ogc:def:crs:OGC:1.3:CRS84" } },
"features": [
{ "type": "Feature", "properties": { "filename": "oregon_672_[-1,-1]_-121.10645625911843_45.544567215562566.png" }, "geometry": { "type": "Point", "coordinates": [ -121.106456259118431, 45.544567215562566 ] } },
{ "type": "Feature", "properties": { "filename": "oregon_672_[-1,0]_-121.09362768346357_45.544567215562566.png" }, "geometry": { "type": "Point", "coordinates": [ -121.093627683463566, 45.544567215562566 ] } },
{ "type": "Feature", "properties": { "filename": "oregon_672_[-1,1]_-121.0807991078087_45.544567215562566.png" }, "geometry": { "type": "Point", "coordinates": [ -121.080799107808701, 45.544567215562566 ] } },
{ "type": "Feature", "properties": { "filename": "oregon_672_[0,-1]_-121.10645625911843_45.55355032731248.png" }, "geometry": { "type": "Point", "coordinates": [ -121.106456259118431, 45.553550327312479 ] } },
{ "type": "Feature", "properties": { "filename": "oregon_672_[0,0]_-121.09362768346357_45.55355032731248.png" }, "geometry": { "type": "Point", "coordinates": [ -121.093627683463566, 45.553550327312479 ] } },
{ "type": "Feature", "properties": { "filename": "oregon_672_[0,1]_-121.0807991078087_45.55355032731248.png" }, "geometry": { "type": "Point", "coordinates": [ -121.080799107808701, 45.553550327312479 ] } },
{ "type": "Feature", "properties": { "filename": "oregon_672_[1,-1]_-121.10645625911843_45.56253343906239.png" }, "geometry": { "type": "Point", "coordinates": [ -121.106456259118431, 45.562533439062392 ] } },
{ "type": "Feature", "properties": { "filename": "oregon_672_[1,0]_-121.09362768346357_45.56253343906239.png" }, "geometry": { "type": "Point", "coordinates": [ -121.093627683463566, 45.562533439062392 ] } },
{ "type": "Feature", "properties": { "filename": "oregon_672_[1,1]_-121.0807991078087_45.56253343906239.png" }, "geometry": { "type": "Point", "coordinates": [ -121.080799107808701, 45.562533439062392 ] } }
]
}
