{
"type": "FeatureCollection",
"crs": { "type": "name", "properties": { "name": "urn:ogc:def:crs:OGC:1.3:CRS84" } },
"features": [
{ "type": "Feature", "properties": { "filename": "oregon_719_[-1,-1]_-117.88870013662807_45.85601593941636.png" }, "geometry": { "type": "Point", "coordinates": [ -117.888700136628074, 45.856015939416359 ] } },
{ "type": "Feature", "properties": { "filename": "oregon_719_[-1,0]_-117.87579987922267_45.85601593941636.png" }, "geometry": { "type": "Point", "coordinates": [ -117.875799879222669, 45.856015939416359 ] } },
{ "type": "Feature", "properties": { "filename": "oregon_719_[-1,1]_-117.86289962181726_45.85601593941636.png" }, "geometry": { "type": "Point", "coordinates": [ -117.862899621817263, 45.856015939416359 ] } },
{ "type": "Feature", "properties": { "filename": "oregon_719_[0,-1]_-117.88870013662807_45.86499905116627.png" }, "geometry": { "type": "Point", "coordinates": [ -117.888700136628074, 45.864999051166272 ] } },
{ "type": "Feature", "properties": { "filename": "oregon_719_[0,0]_-117.87579987922267_45.86499905116627.png" }, "geometry": { "type": "Point", "coordinates": [ -117.875799879222669, 45.864999051166272 ] } },
{ "type": "Feature", "properties": { "filename": "oregon_719_[0,1]_-117.86289962181726_45.86499905116627.png" }, "geometry": { "type": "Point", "coordinates": [ -117.862899621817263, 45.864999051166272 ] } },
{ "type": "Feature", "properties": { "filename": "oregon_719_[1,-1]_-117.88870013662807_45.873982162916185.png" }, "geometry": { "type": "Point", "coordinates": [ -117.888700136628074, 45.873982162916185 ] } },
{ "type": "Feature", "properties": { "filename": "oregon_719_[1,0]_-117.87579987922267_45.873982162916185.png" }, "geometry": { "type": "Point", "coordinates": [ -117.875799879222669, 45.873982162916185 ] } },
{ "type": "Feature", "properties": { "filename": "oregon_719_[1,1]_-117.86289962181726_45.873982162916185.png" }, "geometry": { "type": "Point", "coordinates": [ -117.862899621817263, 45.873982162916185 ] } }
]
}
