{
"type": "FeatureCollection",
"crs": { "type": "name", "properties": { "name": "urn:ogc:def:crs:OGC:1.3:CRS84" } },
"features": [
{ "type": "Feature", "properties": { "filename": "oregon_152_[-1,-1]_-119.38013141420768_42.76787849770807.png" }, "geometry": { "type": "Point", "coordinates": [ -119.380131414207682, 42.767878497708068 ] } },
{ "type": "Feature", "properties": { "filename": "oregon_152_[-1,0]_-119.36789291222061_42.76787849770807.png" }, "geometry": { "type": "Point", "coordinates": [ -119.367892912220611, 42.767878497708068 ] } },
{ "type": "Feature", "properties": { "filename": "oregon_152_[-1,1]_-119.35565441023354_42.76787849770807.png" }, "geometry": { "type": "Point", "coordinates": [ -119.355654410233541, 42.767878497708068 ] } },
{ "type": "Feature", "properties": { "filename": "oregon_152_[0,-1]_-119.38013141420768_42.77686160945798.png" }, "geometry": { "type": "Point", "coordinates": [ -119.380131414207682, 42.776861609457981 ] } },
{ "type": "Feature", "properties": { "filename": "oregon_152_[0,0]_-119.36789291222061_42.77686160945798.png" }, "geometry": { "type": "Point", "coordinates": [ -119.367892912220611, 42.776861609457981 ] } },
{ "type": "Feature", "properties": { "filename": "oregon_152_[0,1]_-119.35565441023354_42.77686160945798.png" }, "geometry": { "type": "Point", "coordinates": [ -119.355654410233541, 42.776861609457981 ] } },
{ "type": "Feature", "properties": { "filename": "oregon_152_[1,-1]_-119.38013141420768_42.785844721207894.png" }, "geometry": { "type": "Point", "coordinates": [ -119.380131414207682, 42.785844721207894 ] } },
{ "type": "Feature", "properties": { "filename": "oregon_152_[1,0]_-119.36789291222061_42.785844721207894.png" }, "geometry": { "type": "Point", "coordinates": [ -119.367892912220611, 42.785844721207894 ] } },
{ "type": "Feature", "properties": { "filename": "oregon_152_[1,1]_-119.35565441023354_42.785844721207894.png" }, "geometry": { "type": "Point", "coordinates": [ -119.355654410233541, 42.785844721207894 ] } }
]
}
