{
"type": "FeatureCollection",
"crs": { "type": "name", "properties": { "name": "urn:ogc:def:crs:OGC:1.3:CRS84" } },
"features": [
{ "type": "Feature", "properties": { "filename": "oregon_551_[-1,-1]_-123.83849740589204_45.014440152806706.png" }, "geometry": { "type": "Point", "coordinates": [ -123.838497405892042, 45.014440152806706 ] } },
{ "type": "Feature", "properties": { "filename": "oregon_551_[-1,0]_-123.82578817065941_45.014440152806706.png" }, "geometry": { "type": "Point", "coordinates": [ -123.825788170659408, 45.014440152806706 ] } },
{ "type": "Feature", "properties": { "filename": "oregon_551_[-1,1]_-123.81307893542677_45.014440152806706.png" }, "geometry": { "type": "Point", "coordinates": [ -123.813078935426773, 45.014440152806706 ] } },
{ "type": "Feature", "properties": { "filename": "oregon_551_[0,-1]_-123.83849740589204_45.02342326455662.png" }, "geometry": { "type": "Point", "coordinates": [ -123.838497405892042, 45.023423264556619 ] } },
{ "type": "Feature", "properties": { "filename": "oregon_551_[0,0]_-123.82578817065941_45.02342326455662.png" }, "geometry": { "type": "Point", "coordinates": [ -123.825788170659408, 45.023423264556619 ] } },
{ "type": "Feature", "properties": { "filename": "oregon_551_[0,1]_-123.81307893542677_45.02342326455662.png" }, "geometry": { "type": "Point", "coordinates": [ -123.813078935426773, 45.023423264556619 ] } },
{ "type": "Feature", "properties": { "filename": "oregon_551_[1,-1]_-123.83849740589204_45.03240637630653.png" }, "geometry": { "type": "Point", "coordinates": [ -123.838497405892042, 45.032406376306533 ] } },
{ "type": "Feature", "properties": { "filename": "oregon_551_[1,0]_-123.82578817065941_45.03240637630653.png" }, "geometry": { "type": "Point", "coordinates": [ -123.825788170659408, 45.032406376306533 ] } },
{ "type": "Feature", "properties": { "filename": "oregon_551_[1,1]_-123.81307893542677_45.03240637630653.png" }, "geometry": { "type": "Point", "coordinates": [ -123.813078935426773, 45.032406376306533 ] } }
]
}
