{
"type": "FeatureCollection",
"crs": { "type": "name", "properties": { "name": "urn:ogc:def:crs:OGC:1.3:CRS84" } },
"features": [
{ "type": "Feature", "properties": { "filename": "oregon_172_[-1,-1]_-118.24552586551076_42.81507000304252.png" }, "geometry": { "type": "Point", "coordinates": [ -118.245525865510757, 42.815070003042521 ] } },
{ "type": "Feature", "properties": { "filename": "oregon_172_[-1,0]_-118.23327802543828_42.81507000304252.png" }, "geometry": { "type": "Point", "coordinates": [ -118.233278025438281, 42.815070003042521 ] } },
{ "type": "Feature", "properties": { "filename": "oregon_172_[-1,1]_-118.2210301853658_42.81507000304252.png" }, "geometry": { "type": "Point", "coordinates": [ -118.221030185365805, 42.815070003042521 ] } },
{ "type": "Feature", "properties": { "filename": "oregon_172_[0,-1]_-118.24552586551076_42.824053114792434.png" }, "geometry": { "type": "Point", "coordinates": [ -118.245525865510757, 42.824053114792434 ] } },
{ "type": "Feature", "properties": { "filename": "oregon_172_[0,0]_-118.23327802543828_42.824053114792434.png" }, "geometry": { "type": "Point", "coordinates": [ -118.233278025438281, 42.824053114792434 ] } },
{ "type": "Feature", "properties": { "filename": "oregon_172_[0,1]_-118.2210301853658_42.824053114792434.png" }, "geometry": { "type": "Point", "coordinates": [ -118.221030185365805, 42.824053114792434 ] } },
{ "type": "Feature", "properties": { "filename": "oregon_172_[1,-1]_-118.24552586551076_42.83303622654235.png" }, "geometry": { "type": "Point", "coordinates": [ -118.245525865510757, 42.833036226542347 ] } },
{ "type": "Feature", "properties": { "filename": "oregon_172_[1,0]_-118.23327802543828_42.83303622654235.png" }, "geometry": { "type": "Point", "coordinates": [ -118.233278025438281, 42.833036226542347 ] } },
{ "type": "Feature", "properties": { "filename": "oregon_172_[1,1]_-118.2210301853658_42.83303622654235.png" }, "geometry": { "type": "Point", "coordinates": [ -118.221030185365805, 42.833036226542347 ] } }
]
}
