{
"type": "FeatureCollection",
"crs": { "type": "name", "properties": { "name": "urn:ogc:def:crs:OGC:1.3:CRS84" } },
"features": [
{ "type": "Feature", "properties": { "filename": "oregon_60_[-1,-1]_-117.21044057930882_42.196912260356584.png" }, "geometry": { "type": "Point", "coordinates": [ -117.210440579308823, 42.196912260356584 ] } },
{ "type": "Feature", "properties": { "filename": "oregon_60_[-1,0]_-117.19831329226245_42.196912260356584.png" }, "geometry": { "type": "Point", "coordinates": [ -117.198313292262455, 42.196912260356584 ] } },
{ "type": "Feature", "properties": { "filename": "oregon_60_[-1,1]_-117.18618600521609_42.196912260356584.png" }, "geometry": { "type": "Point", "coordinates": [ -117.186186005216086, 42.196912260356584 ] } },
{ "type": "Feature", "properties": { "filename": "oregon_60_[0,-1]_-117.21044057930882_42.2058953721065.png" }, "geometry": { "type": "Point", "coordinates": [ -117.210440579308823, 42.205895372106497 ] } },
{ "type": "Feature", "properties": { "filename": "oregon_60_[0,0]_-117.19831329226245_42.2058953721065.png" }, "geometry": { "type": "Point", "coordinates": [ -117.198313292262455, 42.205895372106497 ] } },
{ "type": "Feature", "properties": { "filename": "oregon_60_[0,1]_-117.18618600521609_42.2058953721065.png" }, "geometry": { "type": "Point", "coordinates": [ -117.186186005216086, 42.205895372106497 ] } },
{ "type": "Feature", "properties": { "filename": "oregon_60_[1,-1]_-117.21044057930882_42.21487848385641.png" }, "geometry": { "type": "Point", "coordinates": [ -117.210440579308823, 42.21487848385641 ] } },
{ "type": "Feature", "properties": { "filename": "oregon_60_[1,0]_-117.19831329226245_42.21487848385641.png" }, "geometry": { "type": "Point", "coordinates": [ -117.198313292262455, 42.21487848385641 ] } },
{ "type": "Feature", "properties": { "filename": "oregon_60_[1,1]_-117.18618600521609_42.21487848385641.png" }, "geometry": { "type": "Point", "coordinates": [ -117.186186005216086, 42.21487848385641 ] } }
]
}
