{
"type": "FeatureCollection",
"crs": { "type": "name", "properties": { "name": "urn:ogc:def:crs:OGC:1.3:CRS84" } },
"features": [
{ "type": "Feature", "properties": { "filename": "oregon_23_[-1,-1]_-122.40953561845846_42.10357889448878.png" }, "geometry": { "type": "Point", "coordinates": [ -122.409535618458463, 42.103578894488777 ] } },
{ "type": "Feature", "properties": { "filename": "oregon_23_[-1,0]_-122.39742620541347_42.10357889448878.png" }, "geometry": { "type": "Point", "coordinates": [ -122.397426205413467, 42.103578894488777 ] } },
{ "type": "Feature", "properties": { "filename": "oregon_23_[-1,1]_-122.38531679236847_42.10357889448878.png" }, "geometry": { "type": "Point", "coordinates": [ -122.385316792368471, 42.103578894488777 ] } },
{ "type": "Feature", "properties": { "filename": "oregon_23_[0,-1]_-122.40953561845846_42.11256200623869.png" }, "geometry": { "type": "Point", "coordinates": [ -122.409535618458463, 42.11256200623869 ] } },
{ "type": "Feature", "properties": { "filename": "oregon_23_[0,0]_-122.39742620541347_42.11256200623869.png" }, "geometry": { "type": "Point", "coordinates": [ -122.397426205413467, 42.11256200623869 ] } },
{ "type": "Feature", "properties": { "filename": "oregon_23_[0,1]_-122.38531679236847_42.11256200623869.png" }, "geometry": { "type": "Point", "coordinates": [ -122.385316792368471, 42.11256200623869 ] } },
{ "type": "Feature", "properties": { "filename": "oregon_23_[1,-1]_-122.40953561845846_42.1215451179886.png" }, "geometry": { "type": "Point", "coordinates": [ -122.409535618458463, 42.121545117988603 ] } },
{ "type": "Feature", "properties": { "filename": "oregon_23_[1,0]_-122.39742620541347_42.1215451179886.png" }, "geometry": { "type": "Point", "coordinates": [ -122.397426205413467, 42.121545117988603 ] } },
{ "type": "Feature", "properties": { "filename": "oregon_23_[1,1]_-122.38531679236847_42.1215451179886.png" }, "geometry": { "type": "Point", "coordinates": [ -122.385316792368471, 42.121545117988603 ] } }
]
}
