{
"type": "FeatureCollection",
"crs": { "type": "name", "properties": { "name": "urn:ogc:def:crs:OGC:1.3:CRS84" } },
"features": [
{ "type": "Feature", "properties": { "filename": "oregon_288_[-1,-1]_-122.2105122784813_43.546665318723605.png" }, "geometry": { "type": "Point", "coordinates": [ -122.210512278481303, 43.546665318723605 ] } },
{ "type": "Feature", "properties": { "filename": "oregon_288_[-1,0]_-122.19811674377866_43.546665318723605.png" }, "geometry": { "type": "Point", "coordinates": [ -122.198116743778655, 43.546665318723605 ] } },
{ "type": "Feature", "properties": { "filename": "oregon_288_[-1,1]_-122.18572120907601_43.546665318723605.png" }, "geometry": { "type": "Point", "coordinates": [ -122.185721209076007, 43.546665318723605 ] } },
{ "type": "Feature", "properties": { "filename": "oregon_288_[0,-1]_-122.2105122784813_43.55564843047352.png" }, "geometry": { "type": "Point", "coordinates": [ -122.210512278481303, 43.555648430473518 ] } },
{ "type": "Feature", "properties": { "filename": "oregon_288_[0,0]_-122.19811674377866_43.55564843047352.png" }, "geometry": { "type": "Point", "coordinates": [ -122.198116743778655, 43.555648430473518 ] } },
{ "type": "Feature", "properties": { "filename": "oregon_288_[0,1]_-122.18572120907601_43.55564843047352.png" }, "geometry": { "type": "Point", "coordinates": [ -122.185721209076007, 43.555648430473518 ] } },
{ "type": "Feature", "properties": { "filename": "oregon_288_[1,-1]_-122.2105122784813_43.56463154222343.png" }, "geometry": { "type": "Point", "coordinates": [ -122.210512278481303, 43.564631542223431 ] } },
{ "type": "Feature", "properties": { "filename": "oregon_288_[1,0]_-122.19811674377866_43.56463154222343.png" }, "geometry": { "type": "Point", "coordinates": [ -122.198116743778655, 43.564631542223431 ] } },
{ "type": "Feature", "properties": { "filename": "oregon_288_[1,1]_-122.18572120907601_43.56463154222343.png" }, "geometry": { "type": "Point", "coordinates": [ -122.185721209076007, 43.564631542223431 ] } }
]
}
