{
"type": "FeatureCollection",
"crs": { "type": "name", "properties": { "name": "urn:ogc:def:crs:OGC:1.3:CRS84" } },
"features": [
{ "type": "Feature", "properties": { "filename": "oregon_4_[-1,-1]_-122.55324552846594_42.09011855689979.png" }, "geometry": { "type": "Point", "coordinates": [ -122.553245528465936, 42.090118556899789 ] } },
{ "type": "Feature", "properties": { "filename": "oregon_4_[-1,0]_-122.54113868617577_42.09011855689979.png" }, "geometry": { "type": "Point", "coordinates": [ -122.541138686175771, 42.090118556899789 ] } },
{ "type": "Feature", "properties": { "filename": "oregon_4_[-1,1]_-122.5290318438856_42.09011855689979.png" }, "geometry": { "type": "Point", "coordinates": [ -122.529031843885605, 42.090118556899789 ] } },
{ "type": "Feature", "properties": { "filename": "oregon_4_[0,-1]_-122.55324552846594_42.0991016686497.png" }, "geometry": { "type": "Point", "coordinates": [ -122.553245528465936, 42.099101668649702 ] } },
{ "type": "Feature", "properties": { "filename": "oregon_4_[0,0]_-122.54113868617577_42.0991016686497.png" }, "geometry": { "type": "Point", "coordinates": [ -122.541138686175771, 42.099101668649702 ] } },
{ "type": "Feature", "properties": { "filename": "oregon_4_[0,1]_-122.5290318438856_42.0991016686497.png" }, "geometry": { "type": "Point", "coordinates": [ -122.529031843885605, 42.099101668649702 ] } },
{ "type": "Feature", "properties": { "filename": "oregon_4_[1,-1]_-122.55324552846594_42.108084780399615.png" }, "geometry": { "type": "Point", "coordinates": [ -122.553245528465936, 42.108084780399615 ] } },
{ "type": "Feature", "properties": { "filename": "oregon_4_[1,0]_-122.54113868617577_42.108084780399615.png" }, "geometry": { "type": "Point", "coordinates": [ -122.541138686175771, 42.108084780399615 ] } },
{ "type": "Feature", "properties": { "filename": "oregon_4_[1,1]_-122.5290318438856_42.108084780399615.png" }, "geometry": { "type": "Point", "coordinates": [ -122.529031843885605, 42.108084780399615 ] } }
]
}
