{
"type": "FeatureCollection",
"crs": { "type": "name", "properties": { "name": "urn:ogc:def:crs:OGC:1.3:CRS84" } },
"features": [
{ "type": "Feature", "properties": { "filename": "oregon_315_[-1,-1]_-120.12511641704454_43.588093822953354.png" }, "geometry": { "type": "Point", "coordinates": [ -120.125116417044538, 43.588093822953354 ] } },
{ "type": "Feature", "properties": { "filename": "oregon_315_[-1,0]_-120.11271235133148_43.588093822953354.png" }, "geometry": { "type": "Point", "coordinates": [ -120.112712351331481, 43.588093822953354 ] } },
{ "type": "Feature", "properties": { "filename": "oregon_315_[-1,1]_-120.10030828561842_43.588093822953354.png" }, "geometry": { "type": "Point", "coordinates": [ -120.100308285618425, 43.588093822953354 ] } },
{ "type": "Feature", "properties": { "filename": "oregon_315_[0,-1]_-120.12511641704454_43.59707693470327.png" }, "geometry": { "type": "Point", "coordinates": [ -120.125116417044538, 43.597076934703267 ] } },
{ "type": "Feature", "properties": { "filename": "oregon_315_[0,0]_-120.11271235133148_43.59707693470327.png" }, "geometry": { "type": "Point", "coordinates": [ -120.112712351331481, 43.597076934703267 ] } },
{ "type": "Feature", "properties": { "filename": "oregon_315_[0,1]_-120.10030828561842_43.59707693470327.png" }, "geometry": { "type": "Point", "coordinates": [ -120.100308285618425, 43.597076934703267 ] } },
{ "type": "Feature", "properties": { "filename": "oregon_315_[1,-1]_-120.12511641704454_43.60606004645318.png" }, "geometry": { "type": "Point", "coordinates": [ -120.125116417044538, 43.60606004645318 ] } },
{ "type": "Feature", "properties": { "filename": "oregon_315_[1,0]_-120.11271235133148_43.60606004645318.png" }, "geometry": { "type": "Point", "coordinates": [ -120.112712351331481, 43.60606004645318 ] } },
{ "type": "Feature", "properties": { "filename": "oregon_315_[1,1]_-120.10030828561842_43.60606004645318.png" }, "geometry": { "type": "Point", "coordinates": [ -120.100308285618425, 43.60606004645318 ] } }
]
}
