{
"type": "FeatureCollection",
"crs": { "type": "name", "properties": { "name": "urn:ogc:def:crs:OGC:1.3:CRS84" } },
"features": [
{ "type": "Feature", "properties": { "filename": "oregon_157_[-1,-1]_-117.46649008799581_42.70475980630709.png" }, "geometry": { "type": "Point", "coordinates": [ -117.466490087995808, 42.704759806307088 ] } },
{ "type": "Feature", "properties": { "filename": "oregon_157_[-1,0]_-117.45426404051906_42.70475980630709.png" }, "geometry": { "type": "Point", "coordinates": [ -117.454264040519064, 42.704759806307088 ] } },
{ "type": "Feature", "properties": { "filename": "oregon_157_[-1,1]_-117.44203799304232_42.70475980630709.png" }, "geometry": { "type": "Point", "coordinates": [ -117.442037993042319, 42.704759806307088 ] } },
{ "type": "Feature", "properties": { "filename": "oregon_157_[0,-1]_-117.46649008799581_42.713742918057.png" }, "geometry": { "type": "Point", "coordinates": [ -117.466490087995808, 42.713742918057001 ] } },
{ "type": "Feature", "properties": { "filename": "oregon_157_[0,0]_-117.45426404051906_42.713742918057.png" }, "geometry": { "type": "Point", "coordinates": [ -117.454264040519064, 42.713742918057001 ] } },
{ "type": "Feature", "properties": { "filename": "oregon_157_[0,1]_-117.44203799304232_42.713742918057.png" }, "geometry": { "type": "Point", "coordinates": [ -117.442037993042319, 42.713742918057001 ] } },
{ "type": "Feature", "properties": { "filename": "oregon_157_[1,-1]_-117.46649008799581_42.722726029806914.png" }, "geometry": { "type": "Point", "coordinates": [ -117.466490087995808, 42.722726029806914 ] } },
{ "type": "Feature", "properties": { "filename": "oregon_157_[1,0]_-117.45426404051906_42.722726029806914.png" }, "geometry": { "type": "Point", "coordinates": [ -117.454264040519064, 42.722726029806914 ] } },
{ "type": "Feature", "properties": { "filename": "oregon_157_[1,1]_-117.44203799304232_42.722726029806914.png" }, "geometry": { "type": "Point", "coordinates": [ -117.442037993042319, 42.722726029806914 ] } }
]
}
