{
"type": "FeatureCollection",
"crs": { "type": "name", "properties": { "name": "urn:ogc:def:crs:OGC:1.3:CRS84" } },
"features": [
{ "type": "Feature", "properties": { "filename": "oregon_589_[-1,-1]_-123.7675913316446_45.20581822602265.png" }, "geometry": { "type": "Point", "coordinates": [ -123.767591331644596, 45.20581822602265 ] } },
{ "type": "Feature", "properties": { "filename": "oregon_589_[-1,0]_-123.7548393967902_45.20581822602265.png" }, "geometry": { "type": "Point", "coordinates": [ -123.754839396790203, 45.20581822602265 ] } },
{ "type": "Feature", "properties": { "filename": "oregon_589_[-1,1]_-123.74208746193581_45.20581822602265.png" }, "geometry": { "type": "Point", "coordinates": [ -123.74208746193581, 45.20581822602265 ] } },
{ "type": "Feature", "properties": { "filename": "oregon_589_[0,-1]_-123.7675913316446_45.21480133777256.png" }, "geometry": { "type": "Point", "coordinates": [ -123.767591331644596, 45.214801337772563 ] } },
{ "type": "Feature", "properties": { "filename": "oregon_589_[0,0]_-123.7548393967902_45.21480133777256.png" }, "geometry": { "type": "Point", "coordinates": [ -123.754839396790203, 45.214801337772563 ] } },
{ "type": "Feature", "properties": { "filename": "oregon_589_[0,1]_-123.74208746193581_45.21480133777256.png" }, "geometry": { "type": "Point", "coordinates": [ -123.74208746193581, 45.214801337772563 ] } },
{ "type": "Feature", "properties": { "filename": "oregon_589_[1,-1]_-123.7675913316446_45.223784449522476.png" }, "geometry": { "type": "Point", "coordinates": [ -123.767591331644596, 45.223784449522476 ] } },
{ "type": "Feature", "properties": { "filename": "oregon_589_[1,0]_-123.7548393967902_45.223784449522476.png" }, "geometry": { "type": "Point", "coordinates": [ -123.754839396790203, 45.223784449522476 ] } },
{ "type": "Feature", "properties": { "filename": "oregon_589_[1,1]_-123.74208746193581_45.223784449522476.png" }, "geometry": { "type": "Point", "coordinates": [ -123.74208746193581, 45.223784449522476 ] } }
]
}
