{
"type": "FeatureCollection",
"crs": { "type": "name", "properties": { "name": "urn:ogc:def:crs:OGC:1.3:CRS84" } },
"features": [
{ "type": "Feature", "properties": { "filename": "oregon_674_[-1,-1]_-120.66822383511408_45.55031233426536.png" }, "geometry": { "type": "Point", "coordinates": [ -120.668223835114077, 45.550312334265357 ] } },
{ "type": "Feature", "properties": { "filename": "oregon_674_[-1,0]_-120.65539394782489_45.55031233426536.png" }, "geometry": { "type": "Point", "coordinates": [ -120.655393947824891, 45.550312334265357 ] } },
{ "type": "Feature", "properties": { "filename": "oregon_674_[-1,1]_-120.6425640605357_45.55031233426536.png" }, "geometry": { "type": "Point", "coordinates": [ -120.642564060535705, 45.550312334265357 ] } },
{ "type": "Feature", "properties": { "filename": "oregon_674_[0,-1]_-120.66822383511408_45.55929544601527.png" }, "geometry": { "type": "Point", "coordinates": [ -120.668223835114077, 45.55929544601527 ] } },
{ "type": "Feature", "properties": { "filename": "oregon_674_[0,0]_-120.65539394782489_45.55929544601527.png" }, "geometry": { "type": "Point", "coordinates": [ -120.655393947824891, 45.55929544601527 ] } },
{ "type": "Feature", "properties": { "filename": "oregon_674_[0,1]_-120.6425640605357_45.55929544601527.png" }, "geometry": { "type": "Point", "coordinates": [ -120.642564060535705, 45.55929544601527 ] } },
{ "type": "Feature", "properties": { "filename": "oregon_674_[1,-1]_-120.66822383511408_45.56827855776518.png" }, "geometry": { "type": "Point", "coordinates": [ -120.668223835114077, 45.568278557765183 ] } },
{ "type": "Feature", "properties": { "filename": "oregon_674_[1,0]_-120.65539394782489_45.56827855776518.png" }, "geometry": { "type": "Point", "coordinates": [ -120.655393947824891, 45.568278557765183 ] } },
{ "type": "Feature", "properties": { "filename": "oregon_674_[1,1]_-120.6425640605357_45.56827855776518.png" }, "geometry": { "type": "Point", "coordinates": [ -120.642564060535705, 45.568278557765183 ] } }
]
}
