{
"type": "FeatureCollection",
"crs": { "type": "name", "properties": { "name": "urn:ogc:def:crs:OGC:1.3:CRS84" } },
"features": [
{ "type": "Feature", "properties": { "filename": "oregon_640_[-1,-1]_-119.90273997547273_45.37251497772929.png" }, "geometry": { "type": "Point", "coordinates": [ -119.902739975472727, 45.372514977729288 ] } },
{ "type": "Feature", "properties": { "filename": "oregon_640_[-1,0]_-119.88995049669117_45.37251497772929.png" }, "geometry": { "type": "Point", "coordinates": [ -119.889950496691171, 45.372514977729288 ] } },
{ "type": "Feature", "properties": { "filename": "oregon_640_[-1,1]_-119.87716101790961_45.37251497772929.png" }, "geometry": { "type": "Point", "coordinates": [ -119.877161017909614, 45.372514977729288 ] } },
{ "type": "Feature", "properties": { "filename": "oregon_640_[0,-1]_-119.90273997547273_45.3814980894792.png" }, "geometry": { "type": "Point", "coordinates": [ -119.902739975472727, 45.381498089479201 ] } },
{ "type": "Feature", "properties": { "filename": "oregon_640_[0,0]_-119.88995049669117_45.3814980894792.png" }, "geometry": { "type": "Point", "coordinates": [ -119.889950496691171, 45.381498089479201 ] } },
{ "type": "Feature", "properties": { "filename": "oregon_640_[0,1]_-119.87716101790961_45.3814980894792.png" }, "geometry": { "type": "Point", "coordinates": [ -119.877161017909614, 45.381498089479201 ] } },
{ "type": "Feature", "properties": { "filename": "oregon_640_[1,-1]_-119.90273997547273_45.390481201229115.png" }, "geometry": { "type": "Point", "coordinates": [ -119.902739975472727, 45.390481201229115 ] } },
{ "type": "Feature", "properties": { "filename": "oregon_640_[1,0]_-119.88995049669117_45.390481201229115.png" }, "geometry": { "type": "Point", "coordinates": [ -119.889950496691171, 45.390481201229115 ] } },
{ "type": "Feature", "properties": { "filename": "oregon_640_[1,1]_-119.87716101790961_45.390481201229115.png" }, "geometry": { "type": "Point", "coordinates": [ -119.877161017909614, 45.390481201229115 ] } }
]
}
