{
"type": "FeatureCollection",
"crs": { "type": "name", "properties": { "name": "urn:ogc:def:crs:OGC:1.3:CRS84" } },
"features": [
{ "type": "Feature", "properties": { "filename": "oregon_492_[-1,-1]_-118.95688591338055_44.58041444102128.png" }, "geometry": { "type": "Point", "coordinates": [ -118.956885913380546, 44.580414441021283 ] } },
{ "type": "Feature", "properties": { "filename": "oregon_492_[-1,0]_-118.94427194651863_44.58041444102128.png" }, "geometry": { "type": "Point", "coordinates": [ -118.944271946518626, 44.580414441021283 ] } },
{ "type": "Feature", "properties": { "filename": "oregon_492_[-1,1]_-118.9316579796567_44.58041444102128.png" }, "geometry": { "type": "Point", "coordinates": [ -118.931657979656705, 44.580414441021283 ] } },
{ "type": "Feature", "properties": { "filename": "oregon_492_[0,-1]_-118.95688591338055_44.589397552771196.png" }, "geometry": { "type": "Point", "coordinates": [ -118.956885913380546, 44.589397552771196 ] } },
{ "type": "Feature", "properties": { "filename": "oregon_492_[0,0]_-118.94427194651863_44.589397552771196.png" }, "geometry": { "type": "Point", "coordinates": [ -118.944271946518626, 44.589397552771196 ] } },
{ "type": "Feature", "properties": { "filename": "oregon_492_[0,1]_-118.9316579796567_44.589397552771196.png" }, "geometry": { "type": "Point", "coordinates": [ -118.931657979656705, 44.589397552771196 ] } },
{ "type": "Feature", "properties": { "filename": "oregon_492_[1,-1]_-118.95688591338055_44.59838066452111.png" }, "geometry": { "type": "Point", "coordinates": [ -118.956885913380546, 44.598380664521109 ] } },
{ "type": "Feature", "properties": { "filename": "oregon_492_[1,0]_-118.94427194651863_44.59838066452111.png" }, "geometry": { "type": "Point", "coordinates": [ -118.944271946518626, 44.598380664521109 ] } },
{ "type": "Feature", "properties": { "filename": "oregon_492_[1,1]_-118.9316579796567_44.59838066452111.png" }, "geometry": { "type": "Point", "coordinates": [ -118.931657979656705, 44.598380664521109 ] } }
]
}
