{
"type": "FeatureCollection",
"crs": { "type": "name", "properties": { "name": "urn:ogc:def:crs:OGC:1.3:CRS84" } },
"features": [
{ "type": "Feature", "properties": { "filename": "oregon_111_[-1,-1]_-118.8480668538039_42.488067000052496.png" }, "geometry": { "type": "Point", "coordinates": [ -118.8480668538039, 42.488067000052496 ] } },
{ "type": "Feature", "properties": { "filename": "oregon_111_[-1,0]_-118.83588325947362_42.488067000052496.png" }, "geometry": { "type": "Point", "coordinates": [ -118.835883259473619, 42.488067000052496 ] } },
{ "type": "Feature", "properties": { "filename": "oregon_111_[-1,1]_-118.82369966514334_42.488067000052496.png" }, "geometry": { "type": "Point", "coordinates": [ -118.823699665143337, 42.488067000052496 ] } },
{ "type": "Feature", "properties": { "filename": "oregon_111_[0,-1]_-118.8480668538039_42.49705011180241.png" }, "geometry": { "type": "Point", "coordinates": [ -118.8480668538039, 42.497050111802409 ] } },
{ "type": "Feature", "properties": { "filename": "oregon_111_[0,0]_-118.83588325947362_42.49705011180241.png" }, "geometry": { "type": "Point", "coordinates": [ -118.835883259473619, 42.497050111802409 ] } },
{ "type": "Feature", "properties": { "filename": "oregon_111_[0,1]_-118.82369966514334_42.49705011180241.png" }, "geometry": { "type": "Point", "coordinates": [ -118.823699665143337, 42.497050111802409 ] } },
{ "type": "Feature", "properties": { "filename": "oregon_111_[1,-1]_-118.8480668538039_42.50603322355232.png" }, "geometry": { "type": "Point", "coordinates": [ -118.8480668538039, 42.506033223552322 ] } },
{ "type": "Feature", "properties": { "filename": "oregon_111_[1,0]_-118.83588325947362_42.50603322355232.png" }, "geometry": { "type": "Point", "coordinates": [ -118.835883259473619, 42.506033223552322 ] } },
{ "type": "Feature", "properties": { "filename": "oregon_111_[1,1]_-118.82369966514334_42.50603322355232.png" }, "geometry": { "type": "Point", "coordinates": [ -118.823699665143337, 42.506033223552322 ] } }
]
}
