{
"type": "FeatureCollection",
"crs": { "type": "name", "properties": { "name": "urn:ogc:def:crs:OGC:1.3:CRS84" } },
"features": [
{ "type": "Feature", "properties": { "filename": "oregon_243_[-1,-1]_-119.70403323355892_43.227892984658894.png" }, "geometry": { "type": "Point", "coordinates": [ -119.704033233558917, 43.227892984658894 ] } },
{ "type": "Feature", "properties": { "filename": "oregon_243_[-1,0]_-119.69170273557208_43.227892984658894.png" }, "geometry": { "type": "Point", "coordinates": [ -119.691702735572079, 43.227892984658894 ] } },
{ "type": "Feature", "properties": { "filename": "oregon_243_[-1,1]_-119.67937223758524_43.227892984658894.png" }, "geometry": { "type": "Point", "coordinates": [ -119.679372237585241, 43.227892984658894 ] } },
{ "type": "Feature", "properties": { "filename": "oregon_243_[0,-1]_-119.70403323355892_43.23687609640881.png" }, "geometry": { "type": "Point", "coordinates": [ -119.704033233558917, 43.236876096408807 ] } },
{ "type": "Feature", "properties": { "filename": "oregon_243_[0,0]_-119.69170273557208_43.23687609640881.png" }, "geometry": { "type": "Point", "coordinates": [ -119.691702735572079, 43.236876096408807 ] } },
{ "type": "Feature", "properties": { "filename": "oregon_243_[0,1]_-119.67937223758524_43.23687609640881.png" }, "geometry": { "type": "Point", "coordinates": [ -119.679372237585241, 43.236876096408807 ] } },
{ "type": "Feature", "properties": { "filename": "oregon_243_[1,-1]_-119.70403323355892_43.24585920815872.png" }, "geometry": { "type": "Point", "coordinates": [ -119.704033233558917, 43.24585920815872 ] } },
{ "type": "Feature", "properties": { "filename": "oregon_243_[1,0]_-119.69170273557208_43.24585920815872.png" }, "geometry": { "type": "Point", "coordinates": [ -119.691702735572079, 43.24585920815872 ] } },
{ "type": "Feature", "properties": { "filename": "oregon_243_[1,1]_-119.67937223758524_43.24585920815872.png" }, "geometry": { "type": "Point", "coordinates": [ -119.679372237585241, 43.24585920815872 ] } }
]
}
