{
"type": "FeatureCollection",
"crs": { "type": "name", "properties": { "name": "urn:ogc:def:crs:OGC:1.3:CRS84" } },
"features": [
{ "type": "Feature", "properties": { "filename": "oregon_84_[-1,-1]_-122.98277444989631_42.465396094605865.png" }, "geometry": { "type": "Point", "coordinates": [ -122.982774449896311, 42.465396094605865 ] } },
{ "type": "Feature", "properties": { "filename": "oregon_84_[-1,0]_-122.97059527003076_42.465396094605865.png" }, "geometry": { "type": "Point", "coordinates": [ -122.970595270030756, 42.465396094605865 ] } },
{ "type": "Feature", "properties": { "filename": "oregon_84_[-1,1]_-122.9584160901652_42.465396094605865.png" }, "geometry": { "type": "Point", "coordinates": [ -122.958416090165201, 42.465396094605865 ] } },
{ "type": "Feature", "properties": { "filename": "oregon_84_[0,-1]_-122.98277444989631_42.47437920635578.png" }, "geometry": { "type": "Point", "coordinates": [ -122.982774449896311, 42.474379206355778 ] } },
{ "type": "Feature", "properties": { "filename": "oregon_84_[0,0]_-122.97059527003076_42.47437920635578.png" }, "geometry": { "type": "Point", "coordinates": [ -122.970595270030756, 42.474379206355778 ] } },
{ "type": "Feature", "properties": { "filename": "oregon_84_[0,1]_-122.9584160901652_42.47437920635578.png" }, "geometry": { "type": "Point", "coordinates": [ -122.958416090165201, 42.474379206355778 ] } },
{ "type": "Feature", "properties": { "filename": "oregon_84_[1,-1]_-122.98277444989631_42.48336231810569.png" }, "geometry": { "type": "Point", "coordinates": [ -122.982774449896311, 42.483362318105691 ] } },
{ "type": "Feature", "properties": { "filename": "oregon_84_[1,0]_-122.97059527003076_42.48336231810569.png" }, "geometry": { "type": "Point", "coordinates": [ -122.970595270030756, 42.483362318105691 ] } },
{ "type": "Feature", "properties": { "filename": "oregon_84_[1,1]_-122.9584160901652_42.48336231810569.png" }, "geometry": { "type": "Point", "coordinates": [ -122.958416090165201, 42.483362318105691 ] } }
]
}
