{
"type": "FeatureCollection",
"crs": { "type": "name", "properties": { "name": "urn:ogc:def:crs:OGC:1.3:CRS84" } },
"features": [
{ "type": "Feature", "properties": { "filename": "oregon_273_[-1,-1]_-120.91752261985387_43.44664945811725.png" }, "geometry": { "type": "Point", "coordinates": [ -120.91752261985387, 43.44664945811725 ] } },
{ "type": "Feature", "properties": { "filename": "oregon_273_[-1,0]_-120.90514760563576_43.44664945811725.png" }, "geometry": { "type": "Point", "coordinates": [ -120.905147605635761, 43.44664945811725 ] } },
{ "type": "Feature", "properties": { "filename": "oregon_273_[-1,1]_-120.89277259141765_43.44664945811725.png" }, "geometry": { "type": "Point", "coordinates": [ -120.892772591417653, 43.44664945811725 ] } },
{ "type": "Feature", "properties": { "filename": "oregon_273_[0,-1]_-120.91752261985387_43.45563256986716.png" }, "geometry": { "type": "Point", "coordinates": [ -120.91752261985387, 43.455632569867163 ] } },
{ "type": "Feature", "properties": { "filename": "oregon_273_[0,0]_-120.90514760563576_43.45563256986716.png" }, "geometry": { "type": "Point", "coordinates": [ -120.905147605635761, 43.455632569867163 ] } },
{ "type": "Feature", "properties": { "filename": "oregon_273_[0,1]_-120.89277259141765_43.45563256986716.png" }, "geometry": { "type": "Point", "coordinates": [ -120.892772591417653, 43.455632569867163 ] } },
{ "type": "Feature", "properties": { "filename": "oregon_273_[1,-1]_-120.91752261985387_43.464615681617076.png" }, "geometry": { "type": "Point", "coordinates": [ -120.91752261985387, 43.464615681617076 ] } },
{ "type": "Feature", "properties": { "filename": "oregon_273_[1,0]_-120.90514760563576_43.464615681617076.png" }, "geometry": { "type": "Point", "coordinates": [ -120.905147605635761, 43.464615681617076 ] } },
{ "type": "Feature", "properties": { "filename": "oregon_273_[1,1]_-120.89277259141765_43.464615681617076.png" }, "geometry": { "type": "Point", "coordinates": [ -120.892772591417653, 43.464615681617076 ] } }
]
}
