{
"type": "FeatureCollection",
"crs": { "type": "name", "properties": { "name": "urn:ogc:def:crs:OGC:1.3:CRS84" } },
"features": [
{ "type": "Feature", "properties": { "filename": "oregon_80_[-1,-1]_-117.06533388663965_42.32892912601602.png" }, "geometry": { "type": "Point", "coordinates": [ -117.06533388663965, 42.328929126016021 ] } },
{ "type": "Feature", "properties": { "filename": "oregon_80_[-1,0]_-117.0531811719668_42.32892912601602.png" }, "geometry": { "type": "Point", "coordinates": [ -117.053181171966799, 42.328929126016021 ] } },
{ "type": "Feature", "properties": { "filename": "oregon_80_[-1,1]_-117.04102845729395_42.32892912601602.png" }, "geometry": { "type": "Point", "coordinates": [ -117.041028457293947, 42.328929126016021 ] } },
{ "type": "Feature", "properties": { "filename": "oregon_80_[0,-1]_-117.06533388663965_42.337912237765934.png" }, "geometry": { "type": "Point", "coordinates": [ -117.06533388663965, 42.337912237765934 ] } },
{ "type": "Feature", "properties": { "filename": "oregon_80_[0,0]_-117.0531811719668_42.337912237765934.png" }, "geometry": { "type": "Point", "coordinates": [ -117.053181171966799, 42.337912237765934 ] } },
{ "type": "Feature", "properties": { "filename": "oregon_80_[0,1]_-117.04102845729395_42.337912237765934.png" }, "geometry": { "type": "Point", "coordinates": [ -117.041028457293947, 42.337912237765934 ] } },
{ "type": "Feature", "properties": { "filename": "oregon_80_[1,-1]_-117.06533388663965_42.34689534951585.png" }, "geometry": { "type": "Point", "coordinates": [ -117.06533388663965, 42.346895349515847 ] } },
{ "type": "Feature", "properties": { "filename": "oregon_80_[1,0]_-117.0531811719668_42.34689534951585.png" }, "geometry": { "type": "Point", "coordinates": [ -117.053181171966799, 42.346895349515847 ] } },
{ "type": "Feature", "properties": { "filename": "oregon_80_[1,1]_-117.04102845729395_42.34689534951585.png" }, "geometry": { "type": "Point", "coordinates": [ -117.041028457293947, 42.346895349515847 ] } }
]
}
