{
"type": "FeatureCollection",
"crs": { "type": "name", "properties": { "name": "urn:ogc:def:crs:OGC:1.3:CRS84" } },
"features": [
{ "type": "Feature", "properties": { "filename": "oregon_505_[-1,-1]_-120.70632665058419_44.66444818442375.png" }, "geometry": { "type": "Point", "coordinates": [ -120.706326650584188, 44.664448184423748 ] } },
{ "type": "Feature", "properties": { "filename": "oregon_505_[-1,0]_-120.69369440652702_44.66444818442375.png" }, "geometry": { "type": "Point", "coordinates": [ -120.693694406527015, 44.664448184423748 ] } },
{ "type": "Feature", "properties": { "filename": "oregon_505_[-1,1]_-120.68106216246984_44.66444818442375.png" }, "geometry": { "type": "Point", "coordinates": [ -120.681062162469843, 44.664448184423748 ] } },
{ "type": "Feature", "properties": { "filename": "oregon_505_[0,-1]_-120.70632665058419_44.67343129617366.png" }, "geometry": { "type": "Point", "coordinates": [ -120.706326650584188, 44.673431296173661 ] } },
{ "type": "Feature", "properties": { "filename": "oregon_505_[0,0]_-120.69369440652702_44.67343129617366.png" }, "geometry": { "type": "Point", "coordinates": [ -120.693694406527015, 44.673431296173661 ] } },
{ "type": "Feature", "properties": { "filename": "oregon_505_[0,1]_-120.68106216246984_44.67343129617366.png" }, "geometry": { "type": "Point", "coordinates": [ -120.681062162469843, 44.673431296173661 ] } },
{ "type": "Feature", "properties": { "filename": "oregon_505_[1,-1]_-120.70632665058419_44.682414407923574.png" }, "geometry": { "type": "Point", "coordinates": [ -120.706326650584188, 44.682414407923574 ] } },
{ "type": "Feature", "properties": { "filename": "oregon_505_[1,0]_-120.69369440652702_44.682414407923574.png" }, "geometry": { "type": "Point", "coordinates": [ -120.693694406527015, 44.682414407923574 ] } },
{ "type": "Feature", "properties": { "filename": "oregon_505_[1,1]_-120.68106216246984_44.682414407923574.png" }, "geometry": { "type": "Point", "coordinates": [ -120.681062162469843, 44.682414407923574 ] } }
]
}
