{
"type": "FeatureCollection",
"crs": { "type": "name", "properties": { "name": "urn:ogc:def:crs:OGC:1.3:CRS84" } },
"features": [
{ "type": "Feature", "properties": { "filename": "oregon_599_[-1,-1]_-120.50780894417005_45.15788854371174.png" }, "geometry": { "type": "Point", "coordinates": [ -120.507808944170051, 45.157888543711742 ] } },
{ "type": "Feature", "properties": { "filename": "oregon_599_[-1,0]_-120.49506774348038_45.15788854371174.png" }, "geometry": { "type": "Point", "coordinates": [ -120.495067743480377, 45.157888543711742 ] } },
{ "type": "Feature", "properties": { "filename": "oregon_599_[-1,1]_-120.4823265427907_45.15788854371174.png" }, "geometry": { "type": "Point", "coordinates": [ -120.482326542790702, 45.157888543711742 ] } },
{ "type": "Feature", "properties": { "filename": "oregon_599_[0,-1]_-120.50780894417005_45.166871655461655.png" }, "geometry": { "type": "Point", "coordinates": [ -120.507808944170051, 45.166871655461655 ] } },
{ "type": "Feature", "properties": { "filename": "oregon_599_[0,0]_-120.49506774348038_45.166871655461655.png" }, "geometry": { "type": "Point", "coordinates": [ -120.495067743480377, 45.166871655461655 ] } },
{ "type": "Feature", "properties": { "filename": "oregon_599_[0,1]_-120.4823265427907_45.166871655461655.png" }, "geometry": { "type": "Point", "coordinates": [ -120.482326542790702, 45.166871655461655 ] } },
{ "type": "Feature", "properties": { "filename": "oregon_599_[1,-1]_-120.50780894417005_45.17585476721157.png" }, "geometry": { "type": "Point", "coordinates": [ -120.507808944170051, 45.175854767211568 ] } },
{ "type": "Feature", "properties": { "filename": "oregon_599_[1,0]_-120.49506774348038_45.17585476721157.png" }, "geometry": { "type": "Point", "coordinates": [ -120.495067743480377, 45.175854767211568 ] } },
{ "type": "Feature", "properties": { "filename": "oregon_599_[1,1]_-120.4823265427907_45.17585476721157.png" }, "geometry": { "type": "Point", "coordinates": [ -120.482326542790702, 45.175854767211568 ] } }
]
}
