{
"type": "FeatureCollection",
"crs": { "type": "name", "properties": { "name": "urn:ogc:def:crs:OGC:1.3:CRS84" } },
"features": [
{ "type": "Feature", "properties": { "filename": "oregon_67_[-1,-1]_-122.18696388427892_42.373568204882545.png" }, "geometry": { "type": "Point", "coordinates": [ -122.186963884278924, 42.373568204882545 ] } },
{ "type": "Feature", "properties": { "filename": "oregon_67_[-1,0]_-122.17480253295716_42.373568204882545.png" }, "geometry": { "type": "Point", "coordinates": [ -122.174802532957159, 42.373568204882545 ] } },
{ "type": "Feature", "properties": { "filename": "oregon_67_[-1,1]_-122.1626411816354_42.373568204882545.png" }, "geometry": { "type": "Point", "coordinates": [ -122.162641181635394, 42.373568204882545 ] } },
{ "type": "Feature", "properties": { "filename": "oregon_67_[0,-1]_-122.18696388427892_42.38255131663246.png" }, "geometry": { "type": "Point", "coordinates": [ -122.186963884278924, 42.382551316632458 ] } },
{ "type": "Feature", "properties": { "filename": "oregon_67_[0,0]_-122.17480253295716_42.38255131663246.png" }, "geometry": { "type": "Point", "coordinates": [ -122.174802532957159, 42.382551316632458 ] } },
{ "type": "Feature", "properties": { "filename": "oregon_67_[0,1]_-122.1626411816354_42.38255131663246.png" }, "geometry": { "type": "Point", "coordinates": [ -122.162641181635394, 42.382551316632458 ] } },
{ "type": "Feature", "properties": { "filename": "oregon_67_[1,-1]_-122.18696388427892_42.39153442838237.png" }, "geometry": { "type": "Point", "coordinates": [ -122.186963884278924, 42.391534428382371 ] } },
{ "type": "Feature", "properties": { "filename": "oregon_67_[1,0]_-122.17480253295716_42.39153442838237.png" }, "geometry": { "type": "Point", "coordinates": [ -122.174802532957159, 42.391534428382371 ] } },
{ "type": "Feature", "properties": { "filename": "oregon_67_[1,1]_-122.1626411816354_42.39153442838237.png" }, "geometry": { "type": "Point", "coordinates": [ -122.162641181635394, 42.391534428382371 ] } }
]
}
