{
"type": "FeatureCollection",
"crs": { "type": "name", "properties": { "name": "urn:ogc:def:crs:OGC:1.3:CRS84" } },
"features": [
{ "type": "Feature", "properties": { "filename": "oregon_166_[-1,-1]_-120.98848860281521_42.80575399144768.png" }, "geometry": { "type": "Point", "coordinates": [ -120.98848860281521, 42.805753991447681 ] } },
{ "type": "Feature", "properties": { "filename": "oregon_166_[-1,0]_-120.97624260794855_42.80575399144768.png" }, "geometry": { "type": "Point", "coordinates": [ -120.976242607948549, 42.805753991447681 ] } },
{ "type": "Feature", "properties": { "filename": "oregon_166_[-1,1]_-120.96399661308189_42.80575399144768.png" }, "geometry": { "type": "Point", "coordinates": [ -120.963996613081889, 42.805753991447681 ] } },
{ "type": "Feature", "properties": { "filename": "oregon_166_[0,-1]_-120.98848860281521_42.814737103197594.png" }, "geometry": { "type": "Point", "coordinates": [ -120.98848860281521, 42.814737103197594 ] } },
{ "type": "Feature", "properties": { "filename": "oregon_166_[0,0]_-120.97624260794855_42.814737103197594.png" }, "geometry": { "type": "Point", "coordinates": [ -120.976242607948549, 42.814737103197594 ] } },
{ "type": "Feature", "properties": { "filename": "oregon_166_[0,1]_-120.96399661308189_42.814737103197594.png" }, "geometry": { "type": "Point", "coordinates": [ -120.963996613081889, 42.814737103197594 ] } },
{ "type": "Feature", "properties": { "filename": "oregon_166_[1,-1]_-120.98848860281521_42.82372021494751.png" }, "geometry": { "type": "Point", "coordinates": [ -120.98848860281521, 42.823720214947507 ] } },
{ "type": "Feature", "properties": { "filename": "oregon_166_[1,0]_-120.97624260794855_42.82372021494751.png" }, "geometry": { "type": "Point", "coordinates": [ -120.976242607948549, 42.823720214947507 ] } },
{ "type": "Feature", "properties": { "filename": "oregon_166_[1,1]_-120.96399661308189_42.82372021494751.png" }, "geometry": { "type": "Point", "coordinates": [ -120.963996613081889, 42.823720214947507 ] } }
]
}
