{
"type": "FeatureCollection",
"crs": { "type": "name", "properties": { "name": "urn:ogc:def:crs:OGC:1.3:CRS84" } },
"features": [
{ "type": "Feature", "properties": { "filename": "oregon_382_[-1,-1]_-122.03708299431291_43.99758510910087.png" }, "geometry": { "type": "Point", "coordinates": [ -122.037082994312911, 43.997585109100868 ] } },
{ "type": "Feature", "properties": { "filename": "oregon_382_[-1,0]_-122.02459361672126_43.99758510910087.png" }, "geometry": { "type": "Point", "coordinates": [ -122.024593616721262, 43.997585109100868 ] } },
{ "type": "Feature", "properties": { "filename": "oregon_382_[-1,1]_-122.01210423912961_43.99758510910087.png" }, "geometry": { "type": "Point", "coordinates": [ -122.012104239129613, 43.997585109100868 ] } },
{ "type": "Feature", "properties": { "filename": "oregon_382_[0,-1]_-122.03708299431291_44.00656822085078.png" }, "geometry": { "type": "Point", "coordinates": [ -122.037082994312911, 44.006568220850781 ] } },
{ "type": "Feature", "properties": { "filename": "oregon_382_[0,0]_-122.02459361672126_44.00656822085078.png" }, "geometry": { "type": "Point", "coordinates": [ -122.024593616721262, 44.006568220850781 ] } },
{ "type": "Feature", "properties": { "filename": "oregon_382_[0,1]_-122.01210423912961_44.00656822085078.png" }, "geometry": { "type": "Point", "coordinates": [ -122.012104239129613, 44.006568220850781 ] } },
{ "type": "Feature", "properties": { "filename": "oregon_382_[1,-1]_-122.03708299431291_44.015551332600694.png" }, "geometry": { "type": "Point", "coordinates": [ -122.037082994312911, 44.015551332600694 ] } },
{ "type": "Feature", "properties": { "filename": "oregon_382_[1,0]_-122.02459361672126_44.015551332600694.png" }, "geometry": { "type": "Point", "coordinates": [ -122.024593616721262, 44.015551332600694 ] } },
{ "type": "Feature", "properties": { "filename": "oregon_382_[1,1]_-122.01210423912961_44.015551332600694.png" }, "geometry": { "type": "Point", "coordinates": [ -122.012104239129613, 44.015551332600694 ] } }
]
}
