{
"type": "FeatureCollection",
"crs": { "type": "name", "properties": { "name": "urn:ogc:def:crs:OGC:1.3:CRS84" } },
"features": [
{ "type": "Feature", "properties": { "filename": "oregon_254_[-1,-1]_-122.59149085035156_43.28859725009907.png" }, "geometry": { "type": "Point", "coordinates": [ -122.591490850351562, 43.288597250099073 ] } },
{ "type": "Feature", "properties": { "filename": "oregon_254_[-1,0]_-122.57914804940945_43.28859725009907.png" }, "geometry": { "type": "Point", "coordinates": [ -122.579148049409454, 43.288597250099073 ] } },
{ "type": "Feature", "properties": { "filename": "oregon_254_[-1,1]_-122.56680524846735_43.28859725009907.png" }, "geometry": { "type": "Point", "coordinates": [ -122.566805248467347, 43.288597250099073 ] } },
{ "type": "Feature", "properties": { "filename": "oregon_254_[0,-1]_-122.59149085035156_43.297580361848986.png" }, "geometry": { "type": "Point", "coordinates": [ -122.591490850351562, 43.297580361848986 ] } },
{ "type": "Feature", "properties": { "filename": "oregon_254_[0,0]_-122.57914804940945_43.297580361848986.png" }, "geometry": { "type": "Point", "coordinates": [ -122.579148049409454, 43.297580361848986 ] } },
{ "type": "Feature", "properties": { "filename": "oregon_254_[0,1]_-122.56680524846735_43.297580361848986.png" }, "geometry": { "type": "Point", "coordinates": [ -122.566805248467347, 43.297580361848986 ] } },
{ "type": "Feature", "properties": { "filename": "oregon_254_[1,-1]_-122.59149085035156_43.3065634735989.png" }, "geometry": { "type": "Point", "coordinates": [ -122.591490850351562, 43.306563473598899 ] } },
{ "type": "Feature", "properties": { "filename": "oregon_254_[1,0]_-122.57914804940945_43.3065634735989.png" }, "geometry": { "type": "Point", "coordinates": [ -122.579148049409454, 43.306563473598899 ] } },
{ "type": "Feature", "properties": { "filename": "oregon_254_[1,1]_-122.56680524846735_43.3065634735989.png" }, "geometry": { "type": "Point", "coordinates": [ -122.566805248467347, 43.306563473598899 ] } }
]
}
