{
"type": "FeatureCollection",
"crs": { "type": "name", "properties": { "name": "urn:ogc:def:crs:OGC:1.3:CRS84" } },
"features": [
{ "type": "Feature", "properties": { "filename": "oregon_99_[-1,-1]_-124.00479660433292_42.53599643221042.png" }, "geometry": { "type": "Point", "coordinates": [ -124.004796604332924, 42.535996432210418 ] } },
{ "type": "Feature", "properties": { "filename": "oregon_99_[-1,0]_-123.99260366038264_42.53599643221042.png" }, "geometry": { "type": "Point", "coordinates": [ -123.992603660382642, 42.535996432210418 ] } },
{ "type": "Feature", "properties": { "filename": "oregon_99_[-1,1]_-123.98041071643236_42.53599643221042.png" }, "geometry": { "type": "Point", "coordinates": [ -123.98041071643236, 42.535996432210418 ] } },
{ "type": "Feature", "properties": { "filename": "oregon_99_[0,-1]_-124.00479660433292_42.54497954396033.png" }, "geometry": { "type": "Point", "coordinates": [ -124.004796604332924, 42.544979543960331 ] } },
{ "type": "Feature", "properties": { "filename": "oregon_99_[0,0]_-123.99260366038264_42.54497954396033.png" }, "geometry": { "type": "Point", "coordinates": [ -123.992603660382642, 42.544979543960331 ] } },
{ "type": "Feature", "properties": { "filename": "oregon_99_[0,1]_-123.98041071643236_42.54497954396033.png" }, "geometry": { "type": "Point", "coordinates": [ -123.98041071643236, 42.544979543960331 ] } },
{ "type": "Feature", "properties": { "filename": "oregon_99_[1,-1]_-124.00479660433292_42.553962655710244.png" }, "geometry": { "type": "Point", "coordinates": [ -124.004796604332924, 42.553962655710244 ] } },
{ "type": "Feature", "properties": { "filename": "oregon_99_[1,0]_-123.99260366038264_42.553962655710244.png" }, "geometry": { "type": "Point", "coordinates": [ -123.992603660382642, 42.553962655710244 ] } },
{ "type": "Feature", "properties": { "filename": "oregon_99_[1,1]_-123.98041071643236_42.553962655710244.png" }, "geometry": { "type": "Point", "coordinates": [ -123.98041071643236, 42.553962655710244 ] } }
]
}
