{
"type": "FeatureCollection",
"crs": { "type": "name", "properties": { "name": "urn:ogc:def:crs:OGC:1.3:CRS84" } },
"features": [
{ "type": "Feature", "properties": { "filename": "oregon_109_[-1,-1]_-120.02288998265682_42.50346583468361.png" }, "geometry": { "type": "Point", "coordinates": [ -120.022889982656821, 42.50346583468361 ] } },
{ "type": "Feature", "properties": { "filename": "oregon_109_[-1,0]_-120.01070338696107_42.50346583468361.png" }, "geometry": { "type": "Point", "coordinates": [ -120.010703386961069, 42.50346583468361 ] } },
{ "type": "Feature", "properties": { "filename": "oregon_109_[-1,1]_-119.99851679126532_42.50346583468361.png" }, "geometry": { "type": "Point", "coordinates": [ -119.998516791265317, 42.50346583468361 ] } },
{ "type": "Feature", "properties": { "filename": "oregon_109_[0,-1]_-120.02288998265682_42.51244894643352.png" }, "geometry": { "type": "Point", "coordinates": [ -120.022889982656821, 42.512448946433523 ] } },
{ "type": "Feature", "properties": { "filename": "oregon_109_[0,0]_-120.01070338696107_42.51244894643352.png" }, "geometry": { "type": "Point", "coordinates": [ -120.010703386961069, 42.512448946433523 ] } },
{ "type": "Feature", "properties": { "filename": "oregon_109_[0,1]_-119.99851679126532_42.51244894643352.png" }, "geometry": { "type": "Point", "coordinates": [ -119.998516791265317, 42.512448946433523 ] } },
{ "type": "Feature", "properties": { "filename": "oregon_109_[1,-1]_-120.02288998265682_42.521432058183436.png" }, "geometry": { "type": "Point", "coordinates": [ -120.022889982656821, 42.521432058183436 ] } },
{ "type": "Feature", "properties": { "filename": "oregon_109_[1,0]_-120.01070338696107_42.521432058183436.png" }, "geometry": { "type": "Point", "coordinates": [ -120.010703386961069, 42.521432058183436 ] } },
{ "type": "Feature", "properties": { "filename": "oregon_109_[1,1]_-119.99851679126532_42.521432058183436.png" }, "geometry": { "type": "Point", "coordinates": [ -119.998516791265317, 42.521432058183436 ] } }
]
}
