{
"type": "FeatureCollection",
"crs": { "type": "name", "properties": { "name": "urn:ogc:def:crs:OGC:1.3:CRS84" } },
"features": [
{ "type": "Feature", "properties": { "filename": "oregon_327_[-1,-1]_-123.04184829324653_43.677316239807176.png" }, "geometry": { "type": "Point", "coordinates": [ -123.041848293246531, 43.677316239807176 ] } },
{ "type": "Feature", "properties": { "filename": "oregon_327_[-1,0]_-123.0294257927208_43.677316239807176.png" }, "geometry": { "type": "Point", "coordinates": [ -123.029425792720801, 43.677316239807176 ] } },
{ "type": "Feature", "properties": { "filename": "oregon_327_[-1,1]_-123.01700329219507_43.677316239807176.png" }, "geometry": { "type": "Point", "coordinates": [ -123.017003292195071, 43.677316239807176 ] } },
{ "type": "Feature", "properties": { "filename": "oregon_327_[0,-1]_-123.04184829324653_43.68629935155709.png" }, "geometry": { "type": "Point", "coordinates": [ -123.041848293246531, 43.686299351557089 ] } },
{ "type": "Feature", "properties": { "filename": "oregon_327_[0,0]_-123.0294257927208_43.68629935155709.png" }, "geometry": { "type": "Point", "coordinates": [ -123.029425792720801, 43.686299351557089 ] } },
{ "type": "Feature", "properties": { "filename": "oregon_327_[0,1]_-123.01700329219507_43.68629935155709.png" }, "geometry": { "type": "Point", "coordinates": [ -123.017003292195071, 43.686299351557089 ] } },
{ "type": "Feature", "properties": { "filename": "oregon_327_[1,-1]_-123.04184829324653_43.695282463307.png" }, "geometry": { "type": "Point", "coordinates": [ -123.041848293246531, 43.695282463307002 ] } },
{ "type": "Feature", "properties": { "filename": "oregon_327_[1,0]_-123.0294257927208_43.695282463307.png" }, "geometry": { "type": "Point", "coordinates": [ -123.029425792720801, 43.695282463307002 ] } },
{ "type": "Feature", "properties": { "filename": "oregon_327_[1,1]_-123.01700329219507_43.695282463307.png" }, "geometry": { "type": "Point", "coordinates": [ -123.017003292195071, 43.695282463307002 ] } }
]
}
