{
"type": "FeatureCollection",
"crs": { "type": "name", "properties": { "name": "urn:ogc:def:crs:OGC:1.3:CRS84" } },
"features": [
{ "type": "Feature", "properties": { "filename": "oregon_163_[-1,-1]_-122.57813677461888_42.86272087754402.png" }, "geometry": { "type": "Point", "coordinates": [ -122.578136774618883, 42.862720877544021 ] } },
{ "type": "Feature", "properties": { "filename": "oregon_163_[-1,0]_-122.56587948264912_42.86272087754402.png" }, "geometry": { "type": "Point", "coordinates": [ -122.565879482649123, 42.862720877544021 ] } },
{ "type": "Feature", "properties": { "filename": "oregon_163_[-1,1]_-122.55362219067936_42.86272087754402.png" }, "geometry": { "type": "Point", "coordinates": [ -122.553622190679363, 42.862720877544021 ] } },
{ "type": "Feature", "properties": { "filename": "oregon_163_[0,-1]_-122.57813677461888_42.871703989293934.png" }, "geometry": { "type": "Point", "coordinates": [ -122.578136774618883, 42.871703989293934 ] } },
{ "type": "Feature", "properties": { "filename": "oregon_163_[0,0]_-122.56587948264912_42.871703989293934.png" }, "geometry": { "type": "Point", "coordinates": [ -122.565879482649123, 42.871703989293934 ] } },
{ "type": "Feature", "properties": { "filename": "oregon_163_[0,1]_-122.55362219067936_42.871703989293934.png" }, "geometry": { "type": "Point", "coordinates": [ -122.553622190679363, 42.871703989293934 ] } },
{ "type": "Feature", "properties": { "filename": "oregon_163_[1,-1]_-122.57813677461888_42.88068710104385.png" }, "geometry": { "type": "Point", "coordinates": [ -122.578136774618883, 42.880687101043847 ] } },
{ "type": "Feature", "properties": { "filename": "oregon_163_[1,0]_-122.56587948264912_42.88068710104385.png" }, "geometry": { "type": "Point", "coordinates": [ -122.565879482649123, 42.880687101043847 ] } },
{ "type": "Feature", "properties": { "filename": "oregon_163_[1,1]_-122.55362219067936_42.88068710104385.png" }, "geometry": { "type": "Point", "coordinates": [ -122.553622190679363, 42.880687101043847 ] } }
]
}
