{
"type": "FeatureCollection",
"crs": { "type": "name", "properties": { "name": "urn:ogc:def:crs:OGC:1.3:CRS84" } },
"features": [
{ "type": "Feature", "properties": { "filename": "oregon_115_[-1,-1]_-117.68168786402704_42.52884432652679.png" }, "geometry": { "type": "Point", "coordinates": [ -117.68168786402704, 42.528844326526787 ] } },
{ "type": "Feature", "properties": { "filename": "oregon_115_[-1,0]_-117.66949631669426_42.52884432652679.png" }, "geometry": { "type": "Point", "coordinates": [ -117.669496316694264, 42.528844326526787 ] } },
{ "type": "Feature", "properties": { "filename": "oregon_115_[-1,1]_-117.65730476936149_42.52884432652679.png" }, "geometry": { "type": "Point", "coordinates": [ -117.657304769361488, 42.528844326526787 ] } },
{ "type": "Feature", "properties": { "filename": "oregon_115_[0,-1]_-117.68168786402704_42.5378274382767.png" }, "geometry": { "type": "Point", "coordinates": [ -117.68168786402704, 42.5378274382767 ] } },
{ "type": "Feature", "properties": { "filename": "oregon_115_[0,0]_-117.66949631669426_42.5378274382767.png" }, "geometry": { "type": "Point", "coordinates": [ -117.669496316694264, 42.5378274382767 ] } },
{ "type": "Feature", "properties": { "filename": "oregon_115_[0,1]_-117.65730476936149_42.5378274382767.png" }, "geometry": { "type": "Point", "coordinates": [ -117.657304769361488, 42.5378274382767 ] } },
{ "type": "Feature", "properties": { "filename": "oregon_115_[1,-1]_-117.68168786402704_42.54681055002661.png" }, "geometry": { "type": "Point", "coordinates": [ -117.68168786402704, 42.546810550026613 ] } },
{ "type": "Feature", "properties": { "filename": "oregon_115_[1,0]_-117.66949631669426_42.54681055002661.png" }, "geometry": { "type": "Point", "coordinates": [ -117.669496316694264, 42.546810550026613 ] } },
{ "type": "Feature", "properties": { "filename": "oregon_115_[1,1]_-117.65730476936149_42.54681055002661.png" }, "geometry": { "type": "Point", "coordinates": [ -117.657304769361488, 42.546810550026613 ] } }
]
}
