{
"type": "FeatureCollection",
"crs": { "type": "name", "properties": { "name": "urn:ogc:def:crs:OGC:1.3:CRS84" } },
"features": [
{ "type": "Feature", "properties": { "filename": "oregon_619_[-1,-1]_-119.64560198939398_45.26141519887669.png" }, "geometry": { "type": "Point", "coordinates": [ -119.645601989393981, 45.261415198876691 ] } },
{ "type": "Feature", "properties": { "filename": "oregon_619_[-1,0]_-119.63283756935466_45.26141519887669.png" }, "geometry": { "type": "Point", "coordinates": [ -119.632837569354663, 45.261415198876691 ] } },
{ "type": "Feature", "properties": { "filename": "oregon_619_[-1,1]_-119.62007314931535_45.26141519887669.png" }, "geometry": { "type": "Point", "coordinates": [ -119.620073149315346, 45.261415198876691 ] } },
{ "type": "Feature", "properties": { "filename": "oregon_619_[0,-1]_-119.64560198939398_45.270398310626604.png" }, "geometry": { "type": "Point", "coordinates": [ -119.645601989393981, 45.270398310626604 ] } },
{ "type": "Feature", "properties": { "filename": "oregon_619_[0,0]_-119.63283756935466_45.270398310626604.png" }, "geometry": { "type": "Point", "coordinates": [ -119.632837569354663, 45.270398310626604 ] } },
{ "type": "Feature", "properties": { "filename": "oregon_619_[0,1]_-119.62007314931535_45.270398310626604.png" }, "geometry": { "type": "Point", "coordinates": [ -119.620073149315346, 45.270398310626604 ] } },
{ "type": "Feature", "properties": { "filename": "oregon_619_[1,-1]_-119.64560198939398_45.27938142237652.png" }, "geometry": { "type": "Point", "coordinates": [ -119.645601989393981, 45.279381422376517 ] } },
{ "type": "Feature", "properties": { "filename": "oregon_619_[1,0]_-119.63283756935466_45.27938142237652.png" }, "geometry": { "type": "Point", "coordinates": [ -119.632837569354663, 45.279381422376517 ] } },
{ "type": "Feature", "properties": { "filename": "oregon_619_[1,1]_-119.62007314931535_45.27938142237652.png" }, "geometry": { "type": "Point", "coordinates": [ -119.620073149315346, 45.279381422376517 ] } }
]
}
