{
"type": "FeatureCollection",
"crs": { "type": "name", "properties": { "name": "urn:ogc:def:crs:OGC:1.3:CRS84" } },
"features": [
{ "type": "Feature", "properties": { "filename": "oregon_8_[-1,-1]_-120.62084667597955_42.01957460686292.png" }, "geometry": { "type": "Point", "coordinates": [ -120.62084667597955, 42.019574606862918 ] } },
{ "type": "Feature", "properties": { "filename": "oregon_8_[-1,0]_-120.6087532779578_42.01957460686292.png" }, "geometry": { "type": "Point", "coordinates": [ -120.608753277957803, 42.019574606862918 ] } },
{ "type": "Feature", "properties": { "filename": "oregon_8_[-1,1]_-120.59665987993606_42.01957460686292.png" }, "geometry": { "type": "Point", "coordinates": [ -120.596659879936055, 42.019574606862918 ] } },
{ "type": "Feature", "properties": { "filename": "oregon_8_[0,-1]_-120.62084667597955_42.02855771861283.png" }, "geometry": { "type": "Point", "coordinates": [ -120.62084667597955, 42.028557718612831 ] } },
{ "type": "Feature", "properties": { "filename": "oregon_8_[0,0]_-120.6087532779578_42.02855771861283.png" }, "geometry": { "type": "Point", "coordinates": [ -120.608753277957803, 42.028557718612831 ] } },
{ "type": "Feature", "properties": { "filename": "oregon_8_[0,1]_-120.59665987993606_42.02855771861283.png" }, "geometry": { "type": "Point", "coordinates": [ -120.596659879936055, 42.028557718612831 ] } },
{ "type": "Feature", "properties": { "filename": "oregon_8_[1,-1]_-120.62084667597955_42.037540830362744.png" }, "geometry": { "type": "Point", "coordinates": [ -120.62084667597955, 42.037540830362744 ] } },
{ "type": "Feature", "properties": { "filename": "oregon_8_[1,0]_-120.6087532779578_42.037540830362744.png" }, "geometry": { "type": "Point", "coordinates": [ -120.608753277957803, 42.037540830362744 ] } },
{ "type": "Feature", "properties": { "filename": "oregon_8_[1,1]_-120.59665987993606_42.037540830362744.png" }, "geometry": { "type": "Point", "coordinates": [ -120.596659879936055, 42.037540830362744 ] } }
]
}
