{
"type": "FeatureCollection",
"crs": { "type": "name", "properties": { "name": "urn:ogc:def:crs:OGC:1.3:CRS84" } },
"features": [
{ "type": "Feature", "properties": { "filename": "oregon_208_[-1,-1]_-118.29050487462297_43.0277500118266.png" }, "geometry": { "type": "Point", "coordinates": [ -118.290504874622968, 43.027750011826598 ] } },
{ "type": "Feature", "properties": { "filename": "oregon_208_[-1,0]_-118.27821466903576_43.0277500118266.png" }, "geometry": { "type": "Point", "coordinates": [ -118.278214669035762, 43.027750011826598 ] } },
{ "type": "Feature", "properties": { "filename": "oregon_208_[-1,1]_-118.26592446344856_43.0277500118266.png" }, "geometry": { "type": "Point", "coordinates": [ -118.265924463448556, 43.027750011826598 ] } },
{ "type": "Feature", "properties": { "filename": "oregon_208_[0,-1]_-118.29050487462297_43.03673312357651.png" }, "geometry": { "type": "Point", "coordinates": [ -118.290504874622968, 43.036733123576511 ] } },
{ "type": "Feature", "properties": { "filename": "oregon_208_[0,0]_-118.27821466903576_43.03673312357651.png" }, "geometry": { "type": "Point", "coordinates": [ -118.278214669035762, 43.036733123576511 ] } },
{ "type": "Feature", "properties": { "filename": "oregon_208_[0,1]_-118.26592446344856_43.03673312357651.png" }, "geometry": { "type": "Point", "coordinates": [ -118.265924463448556, 43.036733123576511 ] } },
{ "type": "Feature", "properties": { "filename": "oregon_208_[1,-1]_-118.29050487462297_43.045716235326424.png" }, "geometry": { "type": "Point", "coordinates": [ -118.290504874622968, 43.045716235326424 ] } },
{ "type": "Feature", "properties": { "filename": "oregon_208_[1,0]_-118.27821466903576_43.045716235326424.png" }, "geometry": { "type": "Point", "coordinates": [ -118.278214669035762, 43.045716235326424 ] } },
{ "type": "Feature", "properties": { "filename": "oregon_208_[1,1]_-118.26592446344856_43.045716235326424.png" }, "geometry": { "type": "Point", "coordinates": [ -118.265924463448556, 43.045716235326424 ] } }
]
}
