{
"type": "FeatureCollection",
"crs": { "type": "name", "properties": { "name": "urn:ogc:def:crs:OGC:1.3:CRS84" } },
"features": [
{ "type": "Feature", "properties": { "filename": "oregon_201_[-1,-1]_-120.34701750469159_43.05201414042576.png" }, "geometry": { "type": "Point", "coordinates": [ -120.347017504691593, 43.052014140425761 ] } },
{ "type": "Feature", "properties": { "filename": "oregon_201_[-1,0]_-120.33472243631407_43.05201414042576.png" }, "geometry": { "type": "Point", "coordinates": [ -120.334722436314067, 43.052014140425761 ] } },
{ "type": "Feature", "properties": { "filename": "oregon_201_[-1,1]_-120.32242736793654_43.05201414042576.png" }, "geometry": { "type": "Point", "coordinates": [ -120.322427367936541, 43.052014140425761 ] } },
{ "type": "Feature", "properties": { "filename": "oregon_201_[0,-1]_-120.34701750469159_43.060997252175675.png" }, "geometry": { "type": "Point", "coordinates": [ -120.347017504691593, 43.060997252175675 ] } },
{ "type": "Feature", "properties": { "filename": "oregon_201_[0,0]_-120.33472243631407_43.060997252175675.png" }, "geometry": { "type": "Point", "coordinates": [ -120.334722436314067, 43.060997252175675 ] } },
{ "type": "Feature", "properties": { "filename": "oregon_201_[0,1]_-120.32242736793654_43.060997252175675.png" }, "geometry": { "type": "Point", "coordinates": [ -120.322427367936541, 43.060997252175675 ] } },
{ "type": "Feature", "properties": { "filename": "oregon_201_[1,-1]_-120.34701750469159_43.06998036392559.png" }, "geometry": { "type": "Point", "coordinates": [ -120.347017504691593, 43.069980363925588 ] } },
{ "type": "Feature", "properties": { "filename": "oregon_201_[1,0]_-120.33472243631407_43.06998036392559.png" }, "geometry": { "type": "Point", "coordinates": [ -120.334722436314067, 43.069980363925588 ] } },
{ "type": "Feature", "properties": { "filename": "oregon_201_[1,1]_-120.32242736793654_43.06998036392559.png" }, "geometry": { "type": "Point", "coordinates": [ -120.322427367936541, 43.069980363925588 ] } }
]
}
