{
"type": "FeatureCollection",
"crs": { "type": "name", "properties": { "name": "urn:ogc:def:crs:OGC:1.3:CRS84" } },
"features": [
{ "type": "Feature", "properties": { "filename": "oregon_509_[-1,-1]_-119.48621113138796_44.69793741106909.png" }, "geometry": { "type": "Point", "coordinates": [ -119.486211131387961, 44.697937411069091 ] } },
{ "type": "Feature", "properties": { "filename": "oregon_509_[-1,0]_-119.47357158112942_44.69793741106909.png" }, "geometry": { "type": "Point", "coordinates": [ -119.47357158112942, 44.697937411069091 ] } },
{ "type": "Feature", "properties": { "filename": "oregon_509_[-1,1]_-119.46093203087088_44.69793741106909.png" }, "geometry": { "type": "Point", "coordinates": [ -119.460932030870879, 44.697937411069091 ] } },
{ "type": "Feature", "properties": { "filename": "oregon_509_[0,-1]_-119.48621113138796_44.706920522819004.png" }, "geometry": { "type": "Point", "coordinates": [ -119.486211131387961, 44.706920522819004 ] } },
{ "type": "Feature", "properties": { "filename": "oregon_509_[0,0]_-119.47357158112942_44.706920522819004.png" }, "geometry": { "type": "Point", "coordinates": [ -119.47357158112942, 44.706920522819004 ] } },
{ "type": "Feature", "properties": { "filename": "oregon_509_[0,1]_-119.46093203087088_44.706920522819004.png" }, "geometry": { "type": "Point", "coordinates": [ -119.460932030870879, 44.706920522819004 ] } },
{ "type": "Feature", "properties": { "filename": "oregon_509_[1,-1]_-119.48621113138796_44.71590363456892.png" }, "geometry": { "type": "Point", "coordinates": [ -119.486211131387961, 44.715903634568917 ] } },
{ "type": "Feature", "properties": { "filename": "oregon_509_[1,0]_-119.47357158112942_44.71590363456892.png" }, "geometry": { "type": "Point", "coordinates": [ -119.47357158112942, 44.715903634568917 ] } },
{ "type": "Feature", "properties": { "filename": "oregon_509_[1,1]_-119.46093203087088_44.71590363456892.png" }, "geometry": { "type": "Point", "coordinates": [ -119.460932030870879, 44.715903634568917 ] } }
]
}
