{
"type": "FeatureCollection",
"crs": { "type": "name", "properties": { "name": "urn:ogc:def:crs:OGC:1.3:CRS84" } },
"features": [
{ "type": "Feature", "properties": { "filename": "oregon_644_[-1,-1]_-118.80089531418949_45.33544301606337.png" }, "geometry": { "type": "Point", "coordinates": [ -118.800895314189489, 45.335443016063373 ] } },
{ "type": "Feature", "properties": { "filename": "oregon_644_[-1,0]_-118.78811421332553_45.33544301606337.png" }, "geometry": { "type": "Point", "coordinates": [ -118.788114213325528, 45.335443016063373 ] } },
{ "type": "Feature", "properties": { "filename": "oregon_644_[-1,1]_-118.77533311246157_45.33544301606337.png" }, "geometry": { "type": "Point", "coordinates": [ -118.775333112461567, 45.335443016063373 ] } },
{ "type": "Feature", "properties": { "filename": "oregon_644_[0,-1]_-118.80089531418949_45.344426127813286.png" }, "geometry": { "type": "Point", "coordinates": [ -118.800895314189489, 45.344426127813286 ] } },
{ "type": "Feature", "properties": { "filename": "oregon_644_[0,0]_-118.78811421332553_45.344426127813286.png" }, "geometry": { "type": "Point", "coordinates": [ -118.788114213325528, 45.344426127813286 ] } },
{ "type": "Feature", "properties": { "filename": "oregon_644_[0,1]_-118.77533311246157_45.344426127813286.png" }, "geometry": { "type": "Point", "coordinates": [ -118.775333112461567, 45.344426127813286 ] } },
{ "type": "Feature", "properties": { "filename": "oregon_644_[1,-1]_-118.80089531418949_45.3534092395632.png" }, "geometry": { "type": "Point", "coordinates": [ -118.800895314189489, 45.353409239563199 ] } },
{ "type": "Feature", "properties": { "filename": "oregon_644_[1,0]_-118.78811421332553_45.3534092395632.png" }, "geometry": { "type": "Point", "coordinates": [ -118.788114213325528, 45.353409239563199 ] } },
{ "type": "Feature", "properties": { "filename": "oregon_644_[1,1]_-118.77533311246157_45.3534092395632.png" }, "geometry": { "type": "Point", "coordinates": [ -118.775333112461567, 45.353409239563199 ] } }
]
}
