{
"type": "FeatureCollection",
"crs": { "type": "name", "properties": { "name": "urn:ogc:def:crs:OGC:1.3:CRS84" } },
"features": [
{ "type": "Feature", "properties": { "filename": "oregon_662_[-1,-1]_-119.35021596591605_45.47473634623225.png" }, "geometry": { "type": "Point", "coordinates": [ -119.35021596591605, 45.474736346232248 ] } },
{ "type": "Feature", "properties": { "filename": "oregon_662_[-1,0]_-119.33740330123283_45.47473634623225.png" }, "geometry": { "type": "Point", "coordinates": [ -119.337403301232825, 45.474736346232248 ] } },
{ "type": "Feature", "properties": { "filename": "oregon_662_[-1,1]_-119.3245906365496_45.47473634623225.png" }, "geometry": { "type": "Point", "coordinates": [ -119.324590636549601, 45.474736346232248 ] } },
{ "type": "Feature", "properties": { "filename": "oregon_662_[0,-1]_-119.35021596591605_45.48371945798216.png" }, "geometry": { "type": "Point", "coordinates": [ -119.35021596591605, 45.483719457982161 ] } },
{ "type": "Feature", "properties": { "filename": "oregon_662_[0,0]_-119.33740330123283_45.48371945798216.png" }, "geometry": { "type": "Point", "coordinates": [ -119.337403301232825, 45.483719457982161 ] } },
{ "type": "Feature", "properties": { "filename": "oregon_662_[0,1]_-119.3245906365496_45.48371945798216.png" }, "geometry": { "type": "Point", "coordinates": [ -119.324590636549601, 45.483719457982161 ] } },
{ "type": "Feature", "properties": { "filename": "oregon_662_[1,-1]_-119.35021596591605_45.492702569732074.png" }, "geometry": { "type": "Point", "coordinates": [ -119.35021596591605, 45.492702569732074 ] } },
{ "type": "Feature", "properties": { "filename": "oregon_662_[1,0]_-119.33740330123283_45.492702569732074.png" }, "geometry": { "type": "Point", "coordinates": [ -119.337403301232825, 45.492702569732074 ] } },
{ "type": "Feature", "properties": { "filename": "oregon_662_[1,1]_-119.3245906365496_45.492702569732074.png" }, "geometry": { "type": "Point", "coordinates": [ -119.324590636549601, 45.492702569732074 ] } }
]
}
