{
"type": "FeatureCollection",
"crs": { "type": "name", "properties": { "name": "urn:ogc:def:crs:OGC:1.3:CRS84" } },
"features": [
{ "type": "Feature", "properties": { "filename": "oregon_671_[-1,-1]_-121.98702452238658_45.554935387336535.png" }, "geometry": { "type": "Point", "coordinates": [ -121.987024522386577, 45.554935387336535 ] } },
{ "type": "Feature", "properties": { "filename": "oregon_671_[-1,0]_-121.97419357934685_45.554935387336535.png" }, "geometry": { "type": "Point", "coordinates": [ -121.974193579346846, 45.554935387336535 ] } },
{ "type": "Feature", "properties": { "filename": "oregon_671_[-1,1]_-121.96136263630711_45.554935387336535.png" }, "geometry": { "type": "Point", "coordinates": [ -121.961362636307115, 45.554935387336535 ] } },
{ "type": "Feature", "properties": { "filename": "oregon_671_[0,-1]_-121.98702452238658_45.56391849908645.png" }, "geometry": { "type": "Point", "coordinates": [ -121.987024522386577, 45.563918499086448 ] } },
{ "type": "Feature", "properties": { "filename": "oregon_671_[0,0]_-121.97419357934685_45.56391849908645.png" }, "geometry": { "type": "Point", "coordinates": [ -121.974193579346846, 45.563918499086448 ] } },
{ "type": "Feature", "properties": { "filename": "oregon_671_[0,1]_-121.96136263630711_45.56391849908645.png" }, "geometry": { "type": "Point", "coordinates": [ -121.961362636307115, 45.563918499086448 ] } },
{ "type": "Feature", "properties": { "filename": "oregon_671_[1,-1]_-121.98702452238658_45.57290161083636.png" }, "geometry": { "type": "Point", "coordinates": [ -121.987024522386577, 45.572901610836361 ] } },
{ "type": "Feature", "properties": { "filename": "oregon_671_[1,0]_-121.97419357934685_45.57290161083636.png" }, "geometry": { "type": "Point", "coordinates": [ -121.974193579346846, 45.572901610836361 ] } },
{ "type": "Feature", "properties": { "filename": "oregon_671_[1,1]_-121.96136263630711_45.57290161083636.png" }, "geometry": { "type": "Point", "coordinates": [ -121.961362636307115, 45.572901610836361 ] } }
]
}
