{
"type": "FeatureCollection",
"crs": { "type": "name", "properties": { "name": "urn:ogc:def:crs:OGC:1.3:CRS84" } },
"features": [
{ "type": "Feature", "properties": { "filename": "oregon_280_[-1,-1]_-118.55733203470562_43.36279380755421.png" }, "geometry": { "type": "Point", "coordinates": [ -118.557332034705624, 43.362793807554212 ] } },
{ "type": "Feature", "properties": { "filename": "oregon_280_[-1,0]_-118.54497414407635_43.36279380755421.png" }, "geometry": { "type": "Point", "coordinates": [ -118.544974144076349, 43.362793807554212 ] } },
{ "type": "Feature", "properties": { "filename": "oregon_280_[-1,1]_-118.53261625344707_43.36279380755421.png" }, "geometry": { "type": "Point", "coordinates": [ -118.532616253447074, 43.362793807554212 ] } },
{ "type": "Feature", "properties": { "filename": "oregon_280_[0,-1]_-118.55733203470562_43.371776919304125.png" }, "geometry": { "type": "Point", "coordinates": [ -118.557332034705624, 43.371776919304125 ] } },
{ "type": "Feature", "properties": { "filename": "oregon_280_[0,0]_-118.54497414407635_43.371776919304125.png" }, "geometry": { "type": "Point", "coordinates": [ -118.544974144076349, 43.371776919304125 ] } },
{ "type": "Feature", "properties": { "filename": "oregon_280_[0,1]_-118.53261625344707_43.371776919304125.png" }, "geometry": { "type": "Point", "coordinates": [ -118.532616253447074, 43.371776919304125 ] } },
{ "type": "Feature", "properties": { "filename": "oregon_280_[1,-1]_-118.55733203470562_43.38076003105404.png" }, "geometry": { "type": "Point", "coordinates": [ -118.557332034705624, 43.380760031054038 ] } },
{ "type": "Feature", "properties": { "filename": "oregon_280_[1,0]_-118.54497414407635_43.38076003105404.png" }, "geometry": { "type": "Point", "coordinates": [ -118.544974144076349, 43.380760031054038 ] } },
{ "type": "Feature", "properties": { "filename": "oregon_280_[1,1]_-118.53261625344707_43.38076003105404.png" }, "geometry": { "type": "Point", "coordinates": [ -118.532616253447074, 43.380760031054038 ] } }
]
}
