{
"type": "FeatureCollection",
"crs": { "type": "name", "properties": { "name": "urn:ogc:def:crs:OGC:1.3:CRS84" } },
"features": [
{ "type": "Feature", "properties": { "filename": "oregon_383_[-1,-1]_-121.66592399283796_44.04180145157901.png" }, "geometry": { "type": "Point", "coordinates": [ -121.665923992837961, 44.041801451579012 ] } },
{ "type": "Feature", "properties": { "filename": "oregon_383_[-1,0]_-121.65342529483266_44.04180145157901.png" }, "geometry": { "type": "Point", "coordinates": [ -121.653425294832658, 44.041801451579012 ] } },
{ "type": "Feature", "properties": { "filename": "oregon_383_[-1,1]_-121.64092659682736_44.04180145157901.png" }, "geometry": { "type": "Point", "coordinates": [ -121.640926596827356, 44.041801451579012 ] } },
{ "type": "Feature", "properties": { "filename": "oregon_383_[0,-1]_-121.66592399283796_44.050784563328925.png" }, "geometry": { "type": "Point", "coordinates": [ -121.665923992837961, 44.050784563328925 ] } },
{ "type": "Feature", "properties": { "filename": "oregon_383_[0,0]_-121.65342529483266_44.050784563328925.png" }, "geometry": { "type": "Point", "coordinates": [ -121.653425294832658, 44.050784563328925 ] } },
{ "type": "Feature", "properties": { "filename": "oregon_383_[0,1]_-121.64092659682736_44.050784563328925.png" }, "geometry": { "type": "Point", "coordinates": [ -121.640926596827356, 44.050784563328925 ] } },
{ "type": "Feature", "properties": { "filename": "oregon_383_[1,-1]_-121.66592399283796_44.05976767507884.png" }, "geometry": { "type": "Point", "coordinates": [ -121.665923992837961, 44.059767675078838 ] } },
{ "type": "Feature", "properties": { "filename": "oregon_383_[1,0]_-121.65342529483266_44.05976767507884.png" }, "geometry": { "type": "Point", "coordinates": [ -121.653425294832658, 44.059767675078838 ] } },
{ "type": "Feature", "properties": { "filename": "oregon_383_[1,1]_-121.64092659682736_44.05976767507884.png" }, "geometry": { "type": "Point", "coordinates": [ -121.640926596827356, 44.059767675078838 ] } }
]
}
