{
"type": "FeatureCollection",
"crs": { "type": "name", "properties": { "name": "urn:ogc:def:crs:OGC:1.3:CRS84" } },
"features": [
{ "type": "Feature", "properties": { "filename": "oregon_682_[-1,-1]_-118.35667536787098_45.54792337526043.png" }, "geometry": { "type": "Point", "coordinates": [ -118.356675367870977, 45.547923375260432 ] } },
{ "type": "Feature", "properties": { "filename": "oregon_682_[-1,0]_-118.34384602603923_45.54792337526043.png" }, "geometry": { "type": "Point", "coordinates": [ -118.34384602603923, 45.547923375260432 ] } },
{ "type": "Feature", "properties": { "filename": "oregon_682_[-1,1]_-118.33101668420748_45.54792337526043.png" }, "geometry": { "type": "Point", "coordinates": [ -118.331016684207484, 45.547923375260432 ] } },
{ "type": "Feature", "properties": { "filename": "oregon_682_[0,-1]_-118.35667536787098_45.556906487010345.png" }, "geometry": { "type": "Point", "coordinates": [ -118.356675367870977, 45.556906487010345 ] } },
{ "type": "Feature", "properties": { "filename": "oregon_682_[0,0]_-118.34384602603923_45.556906487010345.png" }, "geometry": { "type": "Point", "coordinates": [ -118.34384602603923, 45.556906487010345 ] } },
{ "type": "Feature", "properties": { "filename": "oregon_682_[0,1]_-118.33101668420748_45.556906487010345.png" }, "geometry": { "type": "Point", "coordinates": [ -118.331016684207484, 45.556906487010345 ] } },
{ "type": "Feature", "properties": { "filename": "oregon_682_[1,-1]_-118.35667536787098_45.56588959876026.png" }, "geometry": { "type": "Point", "coordinates": [ -118.356675367870977, 45.565889598760258 ] } },
{ "type": "Feature", "properties": { "filename": "oregon_682_[1,0]_-118.34384602603923_45.56588959876026.png" }, "geometry": { "type": "Point", "coordinates": [ -118.34384602603923, 45.565889598760258 ] } },
{ "type": "Feature", "properties": { "filename": "oregon_682_[1,1]_-118.33101668420748_45.56588959876026.png" }, "geometry": { "type": "Point", "coordinates": [ -118.331016684207484, 45.565889598760258 ] } }
]
}
