{
"type": "FeatureCollection",
"crs": { "type": "name", "properties": { "name": "urn:ogc:def:crs:OGC:1.3:CRS84" } },
"features": [
{ "type": "Feature", "properties": { "filename": "oregon_100_[-1,-1]_-123.79516125015452_42.534150953403866.png" }, "geometry": { "type": "Point", "coordinates": [ -123.795161250154521, 42.534150953403866 ] } },
{ "type": "Feature", "properties": { "filename": "oregon_100_[-1,0]_-123.78296866662637_42.534150953403866.png" }, "geometry": { "type": "Point", "coordinates": [ -123.782968666626374, 42.534150953403866 ] } },
{ "type": "Feature", "properties": { "filename": "oregon_100_[-1,1]_-123.77077608309823_42.534150953403866.png" }, "geometry": { "type": "Point", "coordinates": [ -123.770776083098227, 42.534150953403866 ] } },
{ "type": "Feature", "properties": { "filename": "oregon_100_[0,-1]_-123.79516125015452_42.54313406515378.png" }, "geometry": { "type": "Point", "coordinates": [ -123.795161250154521, 42.543134065153779 ] } },
{ "type": "Feature", "properties": { "filename": "oregon_100_[0,0]_-123.78296866662637_42.54313406515378.png" }, "geometry": { "type": "Point", "coordinates": [ -123.782968666626374, 42.543134065153779 ] } },
{ "type": "Feature", "properties": { "filename": "oregon_100_[0,1]_-123.77077608309823_42.54313406515378.png" }, "geometry": { "type": "Point", "coordinates": [ -123.770776083098227, 42.543134065153779 ] } },
{ "type": "Feature", "properties": { "filename": "oregon_100_[1,-1]_-123.79516125015452_42.55211717690369.png" }, "geometry": { "type": "Point", "coordinates": [ -123.795161250154521, 42.552117176903693 ] } },
{ "type": "Feature", "properties": { "filename": "oregon_100_[1,0]_-123.78296866662637_42.55211717690369.png" }, "geometry": { "type": "Point", "coordinates": [ -123.782968666626374, 42.552117176903693 ] } },
{ "type": "Feature", "properties": { "filename": "oregon_100_[1,1]_-123.77077608309823_42.55211717690369.png" }, "geometry": { "type": "Point", "coordinates": [ -123.770776083098227, 42.552117176903693 ] } }
]
}
