{
"type": "FeatureCollection",
"crs": { "type": "name", "properties": { "name": "urn:ogc:def:crs:OGC:1.3:CRS84" } },
"features": [
{ "type": "Feature", "properties": { "filename": "oregon_191_[-1,-1]_-117.56785509861912_42.945891301951214.png" }, "geometry": { "type": "Point", "coordinates": [ -117.56785509861912, 42.945891301951214 ] } },
{ "type": "Feature", "properties": { "filename": "oregon_191_[-1,0]_-117.55558125382748_42.945891301951214.png" }, "geometry": { "type": "Point", "coordinates": [ -117.555581253827484, 42.945891301951214 ] } },
{ "type": "Feature", "properties": { "filename": "oregon_191_[-1,1]_-117.54330740903585_42.945891301951214.png" }, "geometry": { "type": "Point", "coordinates": [ -117.543307409035847, 42.945891301951214 ] } },
{ "type": "Feature", "properties": { "filename": "oregon_191_[0,-1]_-117.56785509861912_42.95487441370113.png" }, "geometry": { "type": "Point", "coordinates": [ -117.56785509861912, 42.954874413701127 ] } },
{ "type": "Feature", "properties": { "filename": "oregon_191_[0,0]_-117.55558125382748_42.95487441370113.png" }, "geometry": { "type": "Point", "coordinates": [ -117.555581253827484, 42.954874413701127 ] } },
{ "type": "Feature", "properties": { "filename": "oregon_191_[0,1]_-117.54330740903585_42.95487441370113.png" }, "geometry": { "type": "Point", "coordinates": [ -117.543307409035847, 42.954874413701127 ] } },
{ "type": "Feature", "properties": { "filename": "oregon_191_[1,-1]_-117.56785509861912_42.96385752545104.png" }, "geometry": { "type": "Point", "coordinates": [ -117.56785509861912, 42.96385752545104 ] } },
{ "type": "Feature", "properties": { "filename": "oregon_191_[1,0]_-117.55558125382748_42.96385752545104.png" }, "geometry": { "type": "Point", "coordinates": [ -117.555581253827484, 42.96385752545104 ] } },
{ "type": "Feature", "properties": { "filename": "oregon_191_[1,1]_-117.54330740903585_42.96385752545104.png" }, "geometry": { "type": "Point", "coordinates": [ -117.543307409035847, 42.96385752545104 ] } }
]
}
