{
"type": "FeatureCollection",
"crs": { "type": "name", "properties": { "name": "urn:ogc:def:crs:OGC:1.3:CRS84" } },
"features": [
{ "type": "Feature", "properties": { "filename": "oregon_147_[-1,-1]_-121.79958606626629_42.7403275727444.png" }, "geometry": { "type": "Point", "coordinates": [ -121.799586066266286, 42.740327572744398 ] } },
{ "type": "Feature", "properties": { "filename": "oregon_147_[-1,0]_-121.78735300554237_42.7403275727444.png" }, "geometry": { "type": "Point", "coordinates": [ -121.787353005542371, 42.740327572744398 ] } },
{ "type": "Feature", "properties": { "filename": "oregon_147_[-1,1]_-121.77511994481846_42.7403275727444.png" }, "geometry": { "type": "Point", "coordinates": [ -121.775119944818456, 42.740327572744398 ] } },
{ "type": "Feature", "properties": { "filename": "oregon_147_[0,-1]_-121.79958606626629_42.74931068449431.png" }, "geometry": { "type": "Point", "coordinates": [ -121.799586066266286, 42.749310684494311 ] } },
{ "type": "Feature", "properties": { "filename": "oregon_147_[0,0]_-121.78735300554237_42.74931068449431.png" }, "geometry": { "type": "Point", "coordinates": [ -121.787353005542371, 42.749310684494311 ] } },
{ "type": "Feature", "properties": { "filename": "oregon_147_[0,1]_-121.77511994481846_42.74931068449431.png" }, "geometry": { "type": "Point", "coordinates": [ -121.775119944818456, 42.749310684494311 ] } },
{ "type": "Feature", "properties": { "filename": "oregon_147_[1,-1]_-121.79958606626629_42.758293796244224.png" }, "geometry": { "type": "Point", "coordinates": [ -121.799586066266286, 42.758293796244224 ] } },
{ "type": "Feature", "properties": { "filename": "oregon_147_[1,0]_-121.78735300554237_42.758293796244224.png" }, "geometry": { "type": "Point", "coordinates": [ -121.787353005542371, 42.758293796244224 ] } },
{ "type": "Feature", "properties": { "filename": "oregon_147_[1,1]_-121.77511994481846_42.758293796244224.png" }, "geometry": { "type": "Point", "coordinates": [ -121.775119944818456, 42.758293796244224 ] } }
]
}
