{
"type": "FeatureCollection",
"crs": { "type": "name", "properties": { "name": "urn:ogc:def:crs:OGC:1.3:CRS84" } },
"features": [
{ "type": "Feature", "properties": { "filename": "oregon_75_[-1,-1]_-118.49197938768077_42.34935543491745.png" }, "geometry": { "type": "Point", "coordinates": [ -118.491979387680772, 42.349355434917449 ] } },
{ "type": "Feature", "properties": { "filename": "oregon_75_[-1,0]_-118.47982272341918_42.34935543491745.png" }, "geometry": { "type": "Point", "coordinates": [ -118.479822723419176, 42.349355434917449 ] } },
{ "type": "Feature", "properties": { "filename": "oregon_75_[-1,1]_-118.46766605915758_42.34935543491745.png" }, "geometry": { "type": "Point", "coordinates": [ -118.46766605915758, 42.349355434917449 ] } },
{ "type": "Feature", "properties": { "filename": "oregon_75_[0,-1]_-118.49197938768077_42.35833854666736.png" }, "geometry": { "type": "Point", "coordinates": [ -118.491979387680772, 42.358338546667362 ] } },
{ "type": "Feature", "properties": { "filename": "oregon_75_[0,0]_-118.47982272341918_42.35833854666736.png" }, "geometry": { "type": "Point", "coordinates": [ -118.479822723419176, 42.358338546667362 ] } },
{ "type": "Feature", "properties": { "filename": "oregon_75_[0,1]_-118.46766605915758_42.35833854666736.png" }, "geometry": { "type": "Point", "coordinates": [ -118.46766605915758, 42.358338546667362 ] } },
{ "type": "Feature", "properties": { "filename": "oregon_75_[1,-1]_-118.49197938768077_42.367321658417275.png" }, "geometry": { "type": "Point", "coordinates": [ -118.491979387680772, 42.367321658417275 ] } },
{ "type": "Feature", "properties": { "filename": "oregon_75_[1,0]_-118.47982272341918_42.367321658417275.png" }, "geometry": { "type": "Point", "coordinates": [ -118.479822723419176, 42.367321658417275 ] } },
{ "type": "Feature", "properties": { "filename": "oregon_75_[1,1]_-118.46766605915758_42.367321658417275.png" }, "geometry": { "type": "Point", "coordinates": [ -118.46766605915758, 42.367321658417275 ] } }
]
}
