{
"type": "FeatureCollection",
"crs": { "type": "name", "properties": { "name": "urn:ogc:def:crs:OGC:1.3:CRS84" } },
"features": [
{ "type": "Feature", "properties": { "filename": "oregon_688_[-1,-1]_-116.69782748934314_45.5080251519981.png" }, "geometry": { "type": "Point", "coordinates": [ -116.69782748934314, 45.508025151998098 ] } },
{ "type": "Feature", "properties": { "filename": "oregon_688_[-1,0]_-116.6850072471026_45.5080251519981.png" }, "geometry": { "type": "Point", "coordinates": [ -116.685007247102604, 45.508025151998098 ] } },
{ "type": "Feature", "properties": { "filename": "oregon_688_[-1,1]_-116.67218700486207_45.5080251519981.png" }, "geometry": { "type": "Point", "coordinates": [ -116.672187004862067, 45.508025151998098 ] } },
{ "type": "Feature", "properties": { "filename": "oregon_688_[0,-1]_-116.69782748934314_45.51700826374801.png" }, "geometry": { "type": "Point", "coordinates": [ -116.69782748934314, 45.517008263748011 ] } },
{ "type": "Feature", "properties": { "filename": "oregon_688_[0,0]_-116.6850072471026_45.51700826374801.png" }, "geometry": { "type": "Point", "coordinates": [ -116.685007247102604, 45.517008263748011 ] } },
{ "type": "Feature", "properties": { "filename": "oregon_688_[0,1]_-116.67218700486207_45.51700826374801.png" }, "geometry": { "type": "Point", "coordinates": [ -116.672187004862067, 45.517008263748011 ] } },
{ "type": "Feature", "properties": { "filename": "oregon_688_[1,-1]_-116.69782748934314_45.525991375497924.png" }, "geometry": { "type": "Point", "coordinates": [ -116.69782748934314, 45.525991375497924 ] } },
{ "type": "Feature", "properties": { "filename": "oregon_688_[1,0]_-116.6850072471026_45.525991375497924.png" }, "geometry": { "type": "Point", "coordinates": [ -116.685007247102604, 45.525991375497924 ] } },
{ "type": "Feature", "properties": { "filename": "oregon_688_[1,1]_-116.67218700486207_45.525991375497924.png" }, "geometry": { "type": "Point", "coordinates": [ -116.672187004862067, 45.525991375497924 ] } }
]
}
