{
"type": "FeatureCollection",
"crs": { "type": "name", "properties": { "name": "urn:ogc:def:crs:OGC:1.3:CRS84" } },
"features": [
{ "type": "Feature", "properties": { "filename": "oregon_107_[-1,-1]_-121.37115540355013_42.50432681260285.png" }, "geometry": { "type": "Point", "coordinates": [ -121.371155403550134, 42.504326812602848 ] } },
{ "type": "Feature", "properties": { "filename": "oregon_107_[-1,0]_-121.35896863997273_42.50432681260285.png" }, "geometry": { "type": "Point", "coordinates": [ -121.35896863997273, 42.504326812602848 ] } },
{ "type": "Feature", "properties": { "filename": "oregon_107_[-1,1]_-121.34678187639533_42.50432681260285.png" }, "geometry": { "type": "Point", "coordinates": [ -121.346781876395326, 42.504326812602848 ] } },
{ "type": "Feature", "properties": { "filename": "oregon_107_[0,-1]_-121.37115540355013_42.51330992435276.png" }, "geometry": { "type": "Point", "coordinates": [ -121.371155403550134, 42.513309924352761 ] } },
{ "type": "Feature", "properties": { "filename": "oregon_107_[0,0]_-121.35896863997273_42.51330992435276.png" }, "geometry": { "type": "Point", "coordinates": [ -121.35896863997273, 42.513309924352761 ] } },
{ "type": "Feature", "properties": { "filename": "oregon_107_[0,1]_-121.34678187639533_42.51330992435276.png" }, "geometry": { "type": "Point", "coordinates": [ -121.346781876395326, 42.513309924352761 ] } },
{ "type": "Feature", "properties": { "filename": "oregon_107_[1,-1]_-121.37115540355013_42.522293036102674.png" }, "geometry": { "type": "Point", "coordinates": [ -121.371155403550134, 42.522293036102674 ] } },
{ "type": "Feature", "properties": { "filename": "oregon_107_[1,0]_-121.35896863997273_42.522293036102674.png" }, "geometry": { "type": "Point", "coordinates": [ -121.35896863997273, 42.522293036102674 ] } },
{ "type": "Feature", "properties": { "filename": "oregon_107_[1,1]_-121.34678187639533_42.522293036102674.png" }, "geometry": { "type": "Point", "coordinates": [ -121.346781876395326, 42.522293036102674 ] } }
]
}
