{
"type": "FeatureCollection",
"crs": { "type": "name", "properties": { "name": "urn:ogc:def:crs:OGC:1.3:CRS84" } },
"features": [
{ "type": "Feature", "properties": { "filename": "oregon_721_[-1,-1]_-117.20027901299434_45.886436359400946.png" }, "geometry": { "type": "Point", "coordinates": [ -117.200279012994343, 45.886436359400946 ] } },
{ "type": "Feature", "properties": { "filename": "oregon_721_[-1,0]_-117.18737169069402_45.886436359400946.png" }, "geometry": { "type": "Point", "coordinates": [ -117.187371690694022, 45.886436359400946 ] } },
{ "type": "Feature", "properties": { "filename": "oregon_721_[-1,1]_-117.1744643683937_45.886436359400946.png" }, "geometry": { "type": "Point", "coordinates": [ -117.1744643683937, 45.886436359400946 ] } },
{ "type": "Feature", "properties": { "filename": "oregon_721_[0,-1]_-117.20027901299434_45.89541947115086.png" }, "geometry": { "type": "Point", "coordinates": [ -117.200279012994343, 45.895419471150859 ] } },
{ "type": "Feature", "properties": { "filename": "oregon_721_[0,0]_-117.18737169069402_45.89541947115086.png" }, "geometry": { "type": "Point", "coordinates": [ -117.187371690694022, 45.895419471150859 ] } },
{ "type": "Feature", "properties": { "filename": "oregon_721_[0,1]_-117.1744643683937_45.89541947115086.png" }, "geometry": { "type": "Point", "coordinates": [ -117.1744643683937, 45.895419471150859 ] } },
{ "type": "Feature", "properties": { "filename": "oregon_721_[1,-1]_-117.20027901299434_45.90440258290077.png" }, "geometry": { "type": "Point", "coordinates": [ -117.200279012994343, 45.904402582900772 ] } },
{ "type": "Feature", "properties": { "filename": "oregon_721_[1,0]_-117.18737169069402_45.90440258290077.png" }, "geometry": { "type": "Point", "coordinates": [ -117.187371690694022, 45.904402582900772 ] } },
{ "type": "Feature", "properties": { "filename": "oregon_721_[1,1]_-117.1744643683937_45.90440258290077.png" }, "geometry": { "type": "Point", "coordinates": [ -117.1744643683937, 45.904402582900772 ] } }
]
}
