{
"type": "FeatureCollection",
"crs": { "type": "name", "properties": { "name": "urn:ogc:def:crs:OGC:1.3:CRS84" } },
"features": [
{ "type": "Feature", "properties": { "filename": "oregon_629_[-1,-1]_-122.49902590382412_45.3720090607852.png" }, "geometry": { "type": "Point", "coordinates": [ -122.499025903824119, 45.372009060785203 ] } },
{ "type": "Feature", "properties": { "filename": "oregon_629_[-1,0]_-122.48623653948503_45.3720090607852.png" }, "geometry": { "type": "Point", "coordinates": [ -122.486236539485034, 45.372009060785203 ] } },
{ "type": "Feature", "properties": { "filename": "oregon_629_[-1,1]_-122.47344717514595_45.3720090607852.png" }, "geometry": { "type": "Point", "coordinates": [ -122.473447175145949, 45.372009060785203 ] } },
{ "type": "Feature", "properties": { "filename": "oregon_629_[0,-1]_-122.49902590382412_45.380992172535116.png" }, "geometry": { "type": "Point", "coordinates": [ -122.499025903824119, 45.380992172535116 ] } },
{ "type": "Feature", "properties": { "filename": "oregon_629_[0,0]_-122.48623653948503_45.380992172535116.png" }, "geometry": { "type": "Point", "coordinates": [ -122.486236539485034, 45.380992172535116 ] } },
{ "type": "Feature", "properties": { "filename": "oregon_629_[0,1]_-122.47344717514595_45.380992172535116.png" }, "geometry": { "type": "Point", "coordinates": [ -122.473447175145949, 45.380992172535116 ] } },
{ "type": "Feature", "properties": { "filename": "oregon_629_[1,-1]_-122.49902590382412_45.38997528428503.png" }, "geometry": { "type": "Point", "coordinates": [ -122.499025903824119, 45.389975284285029 ] } },
{ "type": "Feature", "properties": { "filename": "oregon_629_[1,0]_-122.48623653948503_45.38997528428503.png" }, "geometry": { "type": "Point", "coordinates": [ -122.486236539485034, 45.389975284285029 ] } },
{ "type": "Feature", "properties": { "filename": "oregon_629_[1,1]_-122.47344717514595_45.38997528428503.png" }, "geometry": { "type": "Point", "coordinates": [ -122.473447175145949, 45.389975284285029 ] } }
]
}
