{
"type": "FeatureCollection",
"crs": { "type": "name", "properties": { "name": "urn:ogc:def:crs:OGC:1.3:CRS84" } },
"features": [
{ "type": "Feature", "properties": { "filename": "oregon_731_[-1,-1]_-123.63720778549866_46.06159754591179.png" }, "geometry": { "type": "Point", "coordinates": [ -123.63720778549866, 46.061597545911788 ] } },
{ "type": "Feature", "properties": { "filename": "oregon_731_[-1,0]_-123.62425956122519_46.06159754591179.png" }, "geometry": { "type": "Point", "coordinates": [ -123.624259561225188, 46.061597545911788 ] } },
{ "type": "Feature", "properties": { "filename": "oregon_731_[-1,1]_-123.61131133695172_46.06159754591179.png" }, "geometry": { "type": "Point", "coordinates": [ -123.611311336951715, 46.061597545911788 ] } },
{ "type": "Feature", "properties": { "filename": "oregon_731_[0,-1]_-123.63720778549866_46.0705806576617.png" }, "geometry": { "type": "Point", "coordinates": [ -123.63720778549866, 46.070580657661701 ] } },
{ "type": "Feature", "properties": { "filename": "oregon_731_[0,0]_-123.62425956122519_46.0705806576617.png" }, "geometry": { "type": "Point", "coordinates": [ -123.624259561225188, 46.070580657661701 ] } },
{ "type": "Feature", "properties": { "filename": "oregon_731_[0,1]_-123.61131133695172_46.0705806576617.png" }, "geometry": { "type": "Point", "coordinates": [ -123.611311336951715, 46.070580657661701 ] } },
{ "type": "Feature", "properties": { "filename": "oregon_731_[1,-1]_-123.63720778549866_46.079563769411614.png" }, "geometry": { "type": "Point", "coordinates": [ -123.63720778549866, 46.079563769411614 ] } },
{ "type": "Feature", "properties": { "filename": "oregon_731_[1,0]_-123.62425956122519_46.079563769411614.png" }, "geometry": { "type": "Point", "coordinates": [ -123.624259561225188, 46.079563769411614 ] } },
{ "type": "Feature", "properties": { "filename": "oregon_731_[1,1]_-123.61131133695172_46.079563769411614.png" }, "geometry": { "type": "Point", "coordinates": [ -123.611311336951715, 46.079563769411614 ] } }
]
}
