{
"type": "FeatureCollection",
"crs": { "type": "name", "properties": { "name": "urn:ogc:def:crs:OGC:1.3:CRS84" } },
"features": [
{ "type": "Feature", "properties": { "filename": "oregon_675_[-1,-1]_-120.45582679920193_45.597482063440154.png" }, "geometry": { "type": "Point", "coordinates": [ -120.45582679920193, 45.597482063440154 ] } },
{ "type": "Feature", "properties": { "filename": "oregon_675_[-1,0]_-120.44298612783471_45.597482063440154.png" }, "geometry": { "type": "Point", "coordinates": [ -120.442986127834715, 45.597482063440154 ] } },
{ "type": "Feature", "properties": { "filename": "oregon_675_[-1,1]_-120.4301454564675_45.597482063440154.png" }, "geometry": { "type": "Point", "coordinates": [ -120.4301454564675, 45.597482063440154 ] } },
{ "type": "Feature", "properties": { "filename": "oregon_675_[0,-1]_-120.45582679920193_45.60646517519007.png" }, "geometry": { "type": "Point", "coordinates": [ -120.45582679920193, 45.606465175190067 ] } },
{ "type": "Feature", "properties": { "filename": "oregon_675_[0,0]_-120.44298612783471_45.60646517519007.png" }, "geometry": { "type": "Point", "coordinates": [ -120.442986127834715, 45.606465175190067 ] } },
{ "type": "Feature", "properties": { "filename": "oregon_675_[0,1]_-120.4301454564675_45.60646517519007.png" }, "geometry": { "type": "Point", "coordinates": [ -120.4301454564675, 45.606465175190067 ] } },
{ "type": "Feature", "properties": { "filename": "oregon_675_[1,-1]_-120.45582679920193_45.61544828693998.png" }, "geometry": { "type": "Point", "coordinates": [ -120.45582679920193, 45.61544828693998 ] } },
{ "type": "Feature", "properties": { "filename": "oregon_675_[1,0]_-120.44298612783471_45.61544828693998.png" }, "geometry": { "type": "Point", "coordinates": [ -120.442986127834715, 45.61544828693998 ] } },
{ "type": "Feature", "properties": { "filename": "oregon_675_[1,1]_-120.4301454564675_45.61544828693998.png" }, "geometry": { "type": "Point", "coordinates": [ -120.4301454564675, 45.61544828693998 ] } }
]
}
