{
"type": "FeatureCollection",
"crs": { "type": "name", "properties": { "name": "urn:ogc:def:crs:OGC:1.3:CRS84" } },
"features": [
{ "type": "Feature", "properties": { "filename": "oregon_546_[-1,-1]_-119.36640560966696_44.885577670956934.png" }, "geometry": { "type": "Point", "coordinates": [ -119.366405609666955, 44.885577670956934 ] } },
{ "type": "Feature", "properties": { "filename": "oregon_546_[-1,0]_-119.35372488556112_44.885577670956934.png" }, "geometry": { "type": "Point", "coordinates": [ -119.353724885561121, 44.885577670956934 ] } },
{ "type": "Feature", "properties": { "filename": "oregon_546_[-1,1]_-119.34104416145529_44.885577670956934.png" }, "geometry": { "type": "Point", "coordinates": [ -119.341044161455287, 44.885577670956934 ] } },
{ "type": "Feature", "properties": { "filename": "oregon_546_[0,-1]_-119.36640560966696_44.89456078270685.png" }, "geometry": { "type": "Point", "coordinates": [ -119.366405609666955, 44.894560782706847 ] } },
{ "type": "Feature", "properties": { "filename": "oregon_546_[0,0]_-119.35372488556112_44.89456078270685.png" }, "geometry": { "type": "Point", "coordinates": [ -119.353724885561121, 44.894560782706847 ] } },
{ "type": "Feature", "properties": { "filename": "oregon_546_[0,1]_-119.34104416145529_44.89456078270685.png" }, "geometry": { "type": "Point", "coordinates": [ -119.341044161455287, 44.894560782706847 ] } },
{ "type": "Feature", "properties": { "filename": "oregon_546_[1,-1]_-119.36640560966696_44.90354389445676.png" }, "geometry": { "type": "Point", "coordinates": [ -119.366405609666955, 44.90354389445676 ] } },
{ "type": "Feature", "properties": { "filename": "oregon_546_[1,0]_-119.35372488556112_44.90354389445676.png" }, "geometry": { "type": "Point", "coordinates": [ -119.353724885561121, 44.90354389445676 ] } },
{ "type": "Feature", "properties": { "filename": "oregon_546_[1,1]_-119.34104416145529_44.90354389445676.png" }, "geometry": { "type": "Point", "coordinates": [ -119.341044161455287, 44.90354389445676 ] } }
]
}
