{
"type": "FeatureCollection",
"crs": { "type": "name", "properties": { "name": "urn:ogc:def:crs:OGC:1.3:CRS84" } },
"features": [
{ "type": "Feature", "properties": { "filename": "oregon_82_[-1,-1]_-124.13399424792148_42.43693496616186.png" }, "geometry": { "type": "Point", "coordinates": [ -124.133994247921478, 42.436934966161857 ] } },
{ "type": "Feature", "properties": { "filename": "oregon_82_[-1,0]_-124.12182060276535_42.43693496616186.png" }, "geometry": { "type": "Point", "coordinates": [ -124.121820602765354, 42.436934966161857 ] } },
{ "type": "Feature", "properties": { "filename": "oregon_82_[-1,1]_-124.10964695760923_42.43693496616186.png" }, "geometry": { "type": "Point", "coordinates": [ -124.109646957609229, 42.436934966161857 ] } },
{ "type": "Feature", "properties": { "filename": "oregon_82_[0,-1]_-124.13399424792148_42.44591807791177.png" }, "geometry": { "type": "Point", "coordinates": [ -124.133994247921478, 42.44591807791177 ] } },
{ "type": "Feature", "properties": { "filename": "oregon_82_[0,0]_-124.12182060276535_42.44591807791177.png" }, "geometry": { "type": "Point", "coordinates": [ -124.121820602765354, 42.44591807791177 ] } },
{ "type": "Feature", "properties": { "filename": "oregon_82_[0,1]_-124.10964695760923_42.44591807791177.png" }, "geometry": { "type": "Point", "coordinates": [ -124.109646957609229, 42.44591807791177 ] } },
{ "type": "Feature", "properties": { "filename": "oregon_82_[1,-1]_-124.13399424792148_42.45490118966168.png" }, "geometry": { "type": "Point", "coordinates": [ -124.133994247921478, 42.454901189661683 ] } },
{ "type": "Feature", "properties": { "filename": "oregon_82_[1,0]_-124.12182060276535_42.45490118966168.png" }, "geometry": { "type": "Point", "coordinates": [ -124.121820602765354, 42.454901189661683 ] } },
{ "type": "Feature", "properties": { "filename": "oregon_82_[1,1]_-124.10964695760923_42.45490118966168.png" }, "geometry": { "type": "Point", "coordinates": [ -124.109646957609229, 42.454901189661683 ] } }
]
}
