{
"type": "FeatureCollection",
"crs": { "type": "name", "properties": { "name": "urn:ogc:def:crs:OGC:1.3:CRS84" } },
"features": [
{ "type": "Feature", "properties": { "filename": "oregon_404_[-1,-1]_-120.14649559721742_44.088302338687264.png" }, "geometry": { "type": "Point", "coordinates": [ -120.146495597217424, 44.088302338687264 ] } },
{ "type": "Feature", "properties": { "filename": "oregon_404_[-1,0]_-120.13398707417419_44.088302338687264.png" }, "geometry": { "type": "Point", "coordinates": [ -120.133987074174186, 44.088302338687264 ] } },
{ "type": "Feature", "properties": { "filename": "oregon_404_[-1,1]_-120.12147855113095_44.088302338687264.png" }, "geometry": { "type": "Point", "coordinates": [ -120.121478551130949, 44.088302338687264 ] } },
{ "type": "Feature", "properties": { "filename": "oregon_404_[0,-1]_-120.14649559721742_44.09728545043718.png" }, "geometry": { "type": "Point", "coordinates": [ -120.146495597217424, 44.097285450437177 ] } },
{ "type": "Feature", "properties": { "filename": "oregon_404_[0,0]_-120.13398707417419_44.09728545043718.png" }, "geometry": { "type": "Point", "coordinates": [ -120.133987074174186, 44.097285450437177 ] } },
{ "type": "Feature", "properties": { "filename": "oregon_404_[0,1]_-120.12147855113095_44.09728545043718.png" }, "geometry": { "type": "Point", "coordinates": [ -120.121478551130949, 44.097285450437177 ] } },
{ "type": "Feature", "properties": { "filename": "oregon_404_[1,-1]_-120.14649559721742_44.10626856218709.png" }, "geometry": { "type": "Point", "coordinates": [ -120.146495597217424, 44.10626856218709 ] } },
{ "type": "Feature", "properties": { "filename": "oregon_404_[1,0]_-120.13398707417419_44.10626856218709.png" }, "geometry": { "type": "Point", "coordinates": [ -120.133987074174186, 44.10626856218709 ] } },
{ "type": "Feature", "properties": { "filename": "oregon_404_[1,1]_-120.12147855113095_44.10626856218709.png" }, "geometry": { "type": "Point", "coordinates": [ -120.121478551130949, 44.10626856218709 ] } }
]
}
