{
"type": "FeatureCollection",
"crs": { "type": "name", "properties": { "name": "urn:ogc:def:crs:OGC:1.3:CRS84" } },
"features": [
{ "type": "Feature", "properties": { "filename": "oregon_3_[-1,-1]_-122.97212025036976_42.07038044014319.png" }, "geometry": { "type": "Point", "coordinates": [ -122.972120250369755, 42.07038044014319 ] } },
{ "type": "Feature", "properties": { "filename": "oregon_3_[-1,0]_-122.96001717463031_42.07038044014319.png" }, "geometry": { "type": "Point", "coordinates": [ -122.960017174630309, 42.07038044014319 ] } },
{ "type": "Feature", "properties": { "filename": "oregon_3_[-1,1]_-122.94791409889086_42.07038044014319.png" }, "geometry": { "type": "Point", "coordinates": [ -122.947914098890863, 42.07038044014319 ] } },
{ "type": "Feature", "properties": { "filename": "oregon_3_[0,-1]_-122.97212025036976_42.0793635518931.png" }, "geometry": { "type": "Point", "coordinates": [ -122.972120250369755, 42.079363551893103 ] } },
{ "type": "Feature", "properties": { "filename": "oregon_3_[0,0]_-122.96001717463031_42.0793635518931.png" }, "geometry": { "type": "Point", "coordinates": [ -122.960017174630309, 42.079363551893103 ] } },
{ "type": "Feature", "properties": { "filename": "oregon_3_[0,1]_-122.94791409889086_42.0793635518931.png" }, "geometry": { "type": "Point", "coordinates": [ -122.947914098890863, 42.079363551893103 ] } },
{ "type": "Feature", "properties": { "filename": "oregon_3_[1,-1]_-122.97212025036976_42.088346663643016.png" }, "geometry": { "type": "Point", "coordinates": [ -122.972120250369755, 42.088346663643016 ] } },
{ "type": "Feature", "properties": { "filename": "oregon_3_[1,0]_-122.96001717463031_42.088346663643016.png" }, "geometry": { "type": "Point", "coordinates": [ -122.960017174630309, 42.088346663643016 ] } },
{ "type": "Feature", "properties": { "filename": "oregon_3_[1,1]_-122.94791409889086_42.088346663643016.png" }, "geometry": { "type": "Point", "coordinates": [ -122.947914098890863, 42.088346663643016 ] } }
]
}
