{
"type": "FeatureCollection",
"crs": { "type": "name", "properties": { "name": "urn:ogc:def:crs:OGC:1.3:CRS84" } },
"features": [
{ "type": "Feature", "properties": { "filename": "oregon_609_[-1,-1]_-117.42362398977431_45.13460662209197.png" }, "geometry": { "type": "Point", "coordinates": [ -117.423623989774313, 45.134606622091972 ] } },
{ "type": "Feature", "properties": { "filename": "oregon_609_[-1,0]_-117.41088799348998_45.13460662209197.png" }, "geometry": { "type": "Point", "coordinates": [ -117.410887993489979, 45.134606622091972 ] } },
{ "type": "Feature", "properties": { "filename": "oregon_609_[-1,1]_-117.39815199720564_45.13460662209197.png" }, "geometry": { "type": "Point", "coordinates": [ -117.398151997205645, 45.134606622091972 ] } },
{ "type": "Feature", "properties": { "filename": "oregon_609_[0,-1]_-117.42362398977431_45.143589733841885.png" }, "geometry": { "type": "Point", "coordinates": [ -117.423623989774313, 45.143589733841885 ] } },
{ "type": "Feature", "properties": { "filename": "oregon_609_[0,0]_-117.41088799348998_45.143589733841885.png" }, "geometry": { "type": "Point", "coordinates": [ -117.410887993489979, 45.143589733841885 ] } },
{ "type": "Feature", "properties": { "filename": "oregon_609_[0,1]_-117.39815199720564_45.143589733841885.png" }, "geometry": { "type": "Point", "coordinates": [ -117.398151997205645, 45.143589733841885 ] } },
{ "type": "Feature", "properties": { "filename": "oregon_609_[1,-1]_-117.42362398977431_45.1525728455918.png" }, "geometry": { "type": "Point", "coordinates": [ -117.423623989774313, 45.152572845591799 ] } },
{ "type": "Feature", "properties": { "filename": "oregon_609_[1,0]_-117.41088799348998_45.1525728455918.png" }, "geometry": { "type": "Point", "coordinates": [ -117.410887993489979, 45.152572845591799 ] } },
{ "type": "Feature", "properties": { "filename": "oregon_609_[1,1]_-117.39815199720564_45.1525728455918.png" }, "geometry": { "type": "Point", "coordinates": [ -117.398151997205645, 45.152572845591799 ] } }
]
}
