{
"type": "FeatureCollection",
"crs": { "type": "name", "properties": { "name": "urn:ogc:def:crs:OGC:1.3:CRS84" } },
"features": [
{ "type": "Feature", "properties": { "filename": "oregon_88_[-1,-1]_-121.71890351865497_42.479483459357354.png" }, "geometry": { "type": "Point", "coordinates": [ -121.718903518654969, 42.479483459357354 ] } },
{ "type": "Feature", "properties": { "filename": "oregon_88_[-1,0]_-121.70672159630719_42.479483459357354.png" }, "geometry": { "type": "Point", "coordinates": [ -121.70672159630719, 42.479483459357354 ] } },
{ "type": "Feature", "properties": { "filename": "oregon_88_[-1,1]_-121.69453967395941_42.479483459357354.png" }, "geometry": { "type": "Point", "coordinates": [ -121.694539673959412, 42.479483459357354 ] } },
{ "type": "Feature", "properties": { "filename": "oregon_88_[0,-1]_-121.71890351865497_42.48846657110727.png" }, "geometry": { "type": "Point", "coordinates": [ -121.718903518654969, 42.488466571107267 ] } },
{ "type": "Feature", "properties": { "filename": "oregon_88_[0,0]_-121.70672159630719_42.48846657110727.png" }, "geometry": { "type": "Point", "coordinates": [ -121.70672159630719, 42.488466571107267 ] } },
{ "type": "Feature", "properties": { "filename": "oregon_88_[0,1]_-121.69453967395941_42.48846657110727.png" }, "geometry": { "type": "Point", "coordinates": [ -121.694539673959412, 42.488466571107267 ] } },
{ "type": "Feature", "properties": { "filename": "oregon_88_[1,-1]_-121.71890351865497_42.49744968285718.png" }, "geometry": { "type": "Point", "coordinates": [ -121.718903518654969, 42.49744968285718 ] } },
{ "type": "Feature", "properties": { "filename": "oregon_88_[1,0]_-121.70672159630719_42.49744968285718.png" }, "geometry": { "type": "Point", "coordinates": [ -121.70672159630719, 42.49744968285718 ] } },
{ "type": "Feature", "properties": { "filename": "oregon_88_[1,1]_-121.69453967395941_42.49744968285718.png" }, "geometry": { "type": "Point", "coordinates": [ -121.694539673959412, 42.49744968285718 ] } }
]
}
