{
"type": "FeatureCollection",
"crs": { "type": "name", "properties": { "name": "urn:ogc:def:crs:OGC:1.3:CRS84" } },
"features": [
{ "type": "Feature", "properties": { "filename": "oregon_354_[-1,-1]_-120.1146066447682_43.77660333879839.png" }, "geometry": { "type": "Point", "coordinates": [ -120.114606644768202, 43.776603338798388 ] } },
{ "type": "Feature", "properties": { "filename": "oregon_354_[-1,0]_-120.10216352985094_43.77660333879839.png" }, "geometry": { "type": "Point", "coordinates": [ -120.102163529850941, 43.776603338798388 ] } },
{ "type": "Feature", "properties": { "filename": "oregon_354_[-1,1]_-120.08972041493368_43.77660333879839.png" }, "geometry": { "type": "Point", "coordinates": [ -120.08972041493368, 43.776603338798388 ] } },
{ "type": "Feature", "properties": { "filename": "oregon_354_[0,-1]_-120.1146066447682_43.7855864505483.png" }, "geometry": { "type": "Point", "coordinates": [ -120.114606644768202, 43.785586450548301 ] } },
{ "type": "Feature", "properties": { "filename": "oregon_354_[0,0]_-120.10216352985094_43.7855864505483.png" }, "geometry": { "type": "Point", "coordinates": [ -120.102163529850941, 43.785586450548301 ] } },
{ "type": "Feature", "properties": { "filename": "oregon_354_[0,1]_-120.08972041493368_43.7855864505483.png" }, "geometry": { "type": "Point", "coordinates": [ -120.08972041493368, 43.785586450548301 ] } },
{ "type": "Feature", "properties": { "filename": "oregon_354_[1,-1]_-120.1146066447682_43.794569562298214.png" }, "geometry": { "type": "Point", "coordinates": [ -120.114606644768202, 43.794569562298214 ] } },
{ "type": "Feature", "properties": { "filename": "oregon_354_[1,0]_-120.10216352985094_43.794569562298214.png" }, "geometry": { "type": "Point", "coordinates": [ -120.102163529850941, 43.794569562298214 ] } },
{ "type": "Feature", "properties": { "filename": "oregon_354_[1,1]_-120.08972041493368_43.794569562298214.png" }, "geometry": { "type": "Point", "coordinates": [ -120.08972041493368, 43.794569562298214 ] } }
]
}
