{
"type": "FeatureCollection",
"crs": { "type": "name", "properties": { "name": "urn:ogc:def:crs:OGC:1.3:CRS84" } },
"features": [
{ "type": "Feature", "properties": { "filename": "oregon_649_[-1,-1]_-117.53440366349628_45.365150931078155.png" }, "geometry": { "type": "Point", "coordinates": [ -117.534403663496278, 45.365150931078155 ] } },
{ "type": "Feature", "properties": { "filename": "oregon_649_[-1,0]_-117.5216158502208_45.365150931078155.png" }, "geometry": { "type": "Point", "coordinates": [ -117.521615850220797, 45.365150931078155 ] } },
{ "type": "Feature", "properties": { "filename": "oregon_649_[-1,1]_-117.50882803694532_45.365150931078155.png" }, "geometry": { "type": "Point", "coordinates": [ -117.508828036945317, 45.365150931078155 ] } },
{ "type": "Feature", "properties": { "filename": "oregon_649_[0,-1]_-117.53440366349628_45.37413404282807.png" }, "geometry": { "type": "Point", "coordinates": [ -117.534403663496278, 45.374134042828068 ] } },
{ "type": "Feature", "properties": { "filename": "oregon_649_[0,0]_-117.5216158502208_45.37413404282807.png" }, "geometry": { "type": "Point", "coordinates": [ -117.521615850220797, 45.374134042828068 ] } },
{ "type": "Feature", "properties": { "filename": "oregon_649_[0,1]_-117.50882803694532_45.37413404282807.png" }, "geometry": { "type": "Point", "coordinates": [ -117.508828036945317, 45.374134042828068 ] } },
{ "type": "Feature", "properties": { "filename": "oregon_649_[1,-1]_-117.53440366349628_45.38311715457798.png" }, "geometry": { "type": "Point", "coordinates": [ -117.534403663496278, 45.383117154577981 ] } },
{ "type": "Feature", "properties": { "filename": "oregon_649_[1,0]_-117.5216158502208_45.38311715457798.png" }, "geometry": { "type": "Point", "coordinates": [ -117.521615850220797, 45.383117154577981 ] } },
{ "type": "Feature", "properties": { "filename": "oregon_649_[1,1]_-117.50882803694532_45.38311715457798.png" }, "geometry": { "type": "Point", "coordinates": [ -117.508828036945317, 45.383117154577981 ] } }
]
}
