{
"type": "FeatureCollection",
"crs": { "type": "name", "properties": { "name": "urn:ogc:def:crs:OGC:1.3:CRS84" } },
"features": [
{ "type": "Feature", "properties": { "filename": "oregon_440_[-1,-1]_-119.32126271785778_44.23800970551405.png" }, "geometry": { "type": "Point", "coordinates": [ -119.321262717857778, 44.238009705514052 ] } },
{ "type": "Feature", "properties": { "filename": "oregon_440_[-1,0]_-119.30872240218227_44.23800970551405.png" }, "geometry": { "type": "Point", "coordinates": [ -119.308722402182269, 44.238009705514052 ] } },
{ "type": "Feature", "properties": { "filename": "oregon_440_[-1,1]_-119.29618208650676_44.23800970551405.png" }, "geometry": { "type": "Point", "coordinates": [ -119.296182086506761, 44.238009705514052 ] } },
{ "type": "Feature", "properties": { "filename": "oregon_440_[0,-1]_-119.32126271785778_44.246992817263965.png" }, "geometry": { "type": "Point", "coordinates": [ -119.321262717857778, 44.246992817263965 ] } },
{ "type": "Feature", "properties": { "filename": "oregon_440_[0,0]_-119.30872240218227_44.246992817263965.png" }, "geometry": { "type": "Point", "coordinates": [ -119.308722402182269, 44.246992817263965 ] } },
{ "type": "Feature", "properties": { "filename": "oregon_440_[0,1]_-119.29618208650676_44.246992817263965.png" }, "geometry": { "type": "Point", "coordinates": [ -119.296182086506761, 44.246992817263965 ] } },
{ "type": "Feature", "properties": { "filename": "oregon_440_[1,-1]_-119.32126271785778_44.25597592901388.png" }, "geometry": { "type": "Point", "coordinates": [ -119.321262717857778, 44.255975929013879 ] } },
{ "type": "Feature", "properties": { "filename": "oregon_440_[1,0]_-119.30872240218227_44.25597592901388.png" }, "geometry": { "type": "Point", "coordinates": [ -119.308722402182269, 44.255975929013879 ] } },
{ "type": "Feature", "properties": { "filename": "oregon_440_[1,1]_-119.29618208650676_44.25597592901388.png" }, "geometry": { "type": "Point", "coordinates": [ -119.296182086506761, 44.255975929013879 ] } }
]
}
