{
"type": "FeatureCollection",
"crs": { "type": "name", "properties": { "name": "urn:ogc:def:crs:OGC:1.3:CRS84" } },
"features": [
{ "type": "Feature", "properties": { "filename": "oregon_47_[-1,-1]_-122.53272765763087_42.262335837815286.png" }, "geometry": { "type": "Point", "coordinates": [ -122.532727657630872, 42.262335837815286 ] } },
{ "type": "Feature", "properties": { "filename": "oregon_47_[-1,0]_-122.52058779078885_42.262335837815286.png" }, "geometry": { "type": "Point", "coordinates": [ -122.520587790788852, 42.262335837815286 ] } },
{ "type": "Feature", "properties": { "filename": "oregon_47_[-1,1]_-122.50844792394683_42.262335837815286.png" }, "geometry": { "type": "Point", "coordinates": [ -122.508447923946832, 42.262335837815286 ] } },
{ "type": "Feature", "properties": { "filename": "oregon_47_[0,-1]_-122.53272765763087_42.2713189495652.png" }, "geometry": { "type": "Point", "coordinates": [ -122.532727657630872, 42.271318949565199 ] } },
{ "type": "Feature", "properties": { "filename": "oregon_47_[0,0]_-122.52058779078885_42.2713189495652.png" }, "geometry": { "type": "Point", "coordinates": [ -122.520587790788852, 42.271318949565199 ] } },
{ "type": "Feature", "properties": { "filename": "oregon_47_[0,1]_-122.50844792394683_42.2713189495652.png" }, "geometry": { "type": "Point", "coordinates": [ -122.508447923946832, 42.271318949565199 ] } },
{ "type": "Feature", "properties": { "filename": "oregon_47_[1,-1]_-122.53272765763087_42.28030206131511.png" }, "geometry": { "type": "Point", "coordinates": [ -122.532727657630872, 42.280302061315112 ] } },
{ "type": "Feature", "properties": { "filename": "oregon_47_[1,0]_-122.52058779078885_42.28030206131511.png" }, "geometry": { "type": "Point", "coordinates": [ -122.520587790788852, 42.280302061315112 ] } },
{ "type": "Feature", "properties": { "filename": "oregon_47_[1,1]_-122.50844792394683_42.28030206131511.png" }, "geometry": { "type": "Point", "coordinates": [ -122.508447923946832, 42.280302061315112 ] } }
]
}
