{
"type": "FeatureCollection",
"crs": { "type": "name", "properties": { "name": "urn:ogc:def:crs:OGC:1.3:CRS84" } },
"features": [
{ "type": "Feature", "properties": { "filename": "oregon_263_[-1,-1]_-117.8476011861525_43.33258249264372.png" }, "geometry": { "type": "Point", "coordinates": [ -117.847601186152502, 43.332582492643724 ] } },
{ "type": "Feature", "properties": { "filename": "oregon_263_[-1,0]_-117.835249446685_43.33258249264372.png" }, "geometry": { "type": "Point", "coordinates": [ -117.835249446684998, 43.332582492643724 ] } },
{ "type": "Feature", "properties": { "filename": "oregon_263_[-1,1]_-117.82289770721749_43.33258249264372.png" }, "geometry": { "type": "Point", "coordinates": [ -117.822897707217493, 43.332582492643724 ] } },
{ "type": "Feature", "properties": { "filename": "oregon_263_[0,-1]_-117.8476011861525_43.34156560439364.png" }, "geometry": { "type": "Point", "coordinates": [ -117.847601186152502, 43.341565604393637 ] } },
{ "type": "Feature", "properties": { "filename": "oregon_263_[0,0]_-117.835249446685_43.34156560439364.png" }, "geometry": { "type": "Point", "coordinates": [ -117.835249446684998, 43.341565604393637 ] } },
{ "type": "Feature", "properties": { "filename": "oregon_263_[0,1]_-117.82289770721749_43.34156560439364.png" }, "geometry": { "type": "Point", "coordinates": [ -117.822897707217493, 43.341565604393637 ] } },
{ "type": "Feature", "properties": { "filename": "oregon_263_[1,-1]_-117.8476011861525_43.35054871614355.png" }, "geometry": { "type": "Point", "coordinates": [ -117.847601186152502, 43.35054871614355 ] } },
{ "type": "Feature", "properties": { "filename": "oregon_263_[1,0]_-117.835249446685_43.35054871614355.png" }, "geometry": { "type": "Point", "coordinates": [ -117.835249446684998, 43.35054871614355 ] } },
{ "type": "Feature", "properties": { "filename": "oregon_263_[1,1]_-117.82289770721749_43.35054871614355.png" }, "geometry": { "type": "Point", "coordinates": [ -117.822897707217493, 43.35054871614355 ] } }
]
}
