{
"type": "FeatureCollection",
"crs": { "type": "name", "properties": { "name": "urn:ogc:def:crs:OGC:1.3:CRS84" } },
"features": [
{ "type": "Feature", "properties": { "filename": "oregon_141_[-1,-1]_-124.048503690878_42.762976659731514.png" }, "geometry": { "type": "Point", "coordinates": [ -124.048503690877993, 42.762976659731514 ] } },
{ "type": "Feature", "properties": { "filename": "oregon_141_[-1,0]_-124.03626615755692_42.762976659731514.png" }, "geometry": { "type": "Point", "coordinates": [ -124.036266157556923, 42.762976659731514 ] } },
{ "type": "Feature", "properties": { "filename": "oregon_141_[-1,1]_-124.02402862423585_42.762976659731514.png" }, "geometry": { "type": "Point", "coordinates": [ -124.024028624235854, 42.762976659731514 ] } },
{ "type": "Feature", "properties": { "filename": "oregon_141_[0,-1]_-124.048503690878_42.77195977148143.png" }, "geometry": { "type": "Point", "coordinates": [ -124.048503690877993, 42.771959771481427 ] } },
{ "type": "Feature", "properties": { "filename": "oregon_141_[0,0]_-124.03626615755692_42.77195977148143.png" }, "geometry": { "type": "Point", "coordinates": [ -124.036266157556923, 42.771959771481427 ] } },
{ "type": "Feature", "properties": { "filename": "oregon_141_[0,1]_-124.02402862423585_42.77195977148143.png" }, "geometry": { "type": "Point", "coordinates": [ -124.024028624235854, 42.771959771481427 ] } },
{ "type": "Feature", "properties": { "filename": "oregon_141_[1,-1]_-124.048503690878_42.78094288323134.png" }, "geometry": { "type": "Point", "coordinates": [ -124.048503690877993, 42.78094288323134 ] } },
{ "type": "Feature", "properties": { "filename": "oregon_141_[1,0]_-124.03626615755692_42.78094288323134.png" }, "geometry": { "type": "Point", "coordinates": [ -124.036266157556923, 42.78094288323134 ] } },
{ "type": "Feature", "properties": { "filename": "oregon_141_[1,1]_-124.02402862423585_42.78094288323134.png" }, "geometry": { "type": "Point", "coordinates": [ -124.024028624235854, 42.78094288323134 ] } }
]
}
