{
"type": "FeatureCollection",
"crs": { "type": "name", "properties": { "name": "urn:ogc:def:crs:OGC:1.3:CRS84" } },
"features": [
{ "type": "Feature", "properties": { "filename": "oregon_550_[-1,-1]_-117.36443724614568_44.84025331333401.png" }, "geometry": { "type": "Point", "coordinates": [ -117.364437246145684, 44.84025331333401 ] } },
{ "type": "Feature", "properties": { "filename": "oregon_550_[-1,0]_-117.35176650455861_44.84025331333401.png" }, "geometry": { "type": "Point", "coordinates": [ -117.351766504558611, 44.84025331333401 ] } },
{ "type": "Feature", "properties": { "filename": "oregon_550_[-1,1]_-117.33909576297154_44.84025331333401.png" }, "geometry": { "type": "Point", "coordinates": [ -117.339095762971539, 44.84025331333401 ] } },
{ "type": "Feature", "properties": { "filename": "oregon_550_[0,-1]_-117.36443724614568_44.84923642508392.png" }, "geometry": { "type": "Point", "coordinates": [ -117.364437246145684, 44.849236425083923 ] } },
{ "type": "Feature", "properties": { "filename": "oregon_550_[0,0]_-117.35176650455861_44.84923642508392.png" }, "geometry": { "type": "Point", "coordinates": [ -117.351766504558611, 44.849236425083923 ] } },
{ "type": "Feature", "properties": { "filename": "oregon_550_[0,1]_-117.33909576297154_44.84923642508392.png" }, "geometry": { "type": "Point", "coordinates": [ -117.339095762971539, 44.849236425083923 ] } },
{ "type": "Feature", "properties": { "filename": "oregon_550_[1,-1]_-117.36443724614568_44.858219536833836.png" }, "geometry": { "type": "Point", "coordinates": [ -117.364437246145684, 44.858219536833836 ] } },
{ "type": "Feature", "properties": { "filename": "oregon_550_[1,0]_-117.35176650455861_44.858219536833836.png" }, "geometry": { "type": "Point", "coordinates": [ -117.351766504558611, 44.858219536833836 ] } },
{ "type": "Feature", "properties": { "filename": "oregon_550_[1,1]_-117.33909576297154_44.858219536833836.png" }, "geometry": { "type": "Point", "coordinates": [ -117.339095762971539, 44.858219536833836 ] } }
]
}
