{
"type": "FeatureCollection",
"crs": { "type": "name", "properties": { "name": "urn:ogc:def:crs:OGC:1.3:CRS84" } },
"features": [
{ "type": "Feature", "properties": { "filename": "oregon_386_[-1,-1]_-120.52219261317032_43.99653091362234.png" }, "geometry": { "type": "Point", "coordinates": [ -120.522192613170319, 43.996530913622337 ] } },
{ "type": "Feature", "properties": { "filename": "oregon_386_[-1,0]_-120.50970345753333_43.99653091362234.png" }, "geometry": { "type": "Point", "coordinates": [ -120.509703457533334, 43.996530913622337 ] } },
{ "type": "Feature", "properties": { "filename": "oregon_386_[-1,1]_-120.49721430189635_43.99653091362234.png" }, "geometry": { "type": "Point", "coordinates": [ -120.497214301896349, 43.996530913622337 ] } },
{ "type": "Feature", "properties": { "filename": "oregon_386_[0,-1]_-120.52219261317032_44.00551402537225.png" }, "geometry": { "type": "Point", "coordinates": [ -120.522192613170319, 44.00551402537225 ] } },
{ "type": "Feature", "properties": { "filename": "oregon_386_[0,0]_-120.50970345753333_44.00551402537225.png" }, "geometry": { "type": "Point", "coordinates": [ -120.509703457533334, 44.00551402537225 ] } },
{ "type": "Feature", "properties": { "filename": "oregon_386_[0,1]_-120.49721430189635_44.00551402537225.png" }, "geometry": { "type": "Point", "coordinates": [ -120.497214301896349, 44.00551402537225 ] } },
{ "type": "Feature", "properties": { "filename": "oregon_386_[1,-1]_-120.52219261317032_44.01449713712216.png" }, "geometry": { "type": "Point", "coordinates": [ -120.522192613170319, 44.014497137122163 ] } },
{ "type": "Feature", "properties": { "filename": "oregon_386_[1,0]_-120.50970345753333_44.01449713712216.png" }, "geometry": { "type": "Point", "coordinates": [ -120.509703457533334, 44.014497137122163 ] } },
{ "type": "Feature", "properties": { "filename": "oregon_386_[1,1]_-120.49721430189635_44.01449713712216.png" }, "geometry": { "type": "Point", "coordinates": [ -120.497214301896349, 44.014497137122163 ] } }
]
}
