{
"type": "FeatureCollection",
"crs": { "type": "name", "properties": { "name": "urn:ogc:def:crs:OGC:1.3:CRS84" } },
"features": [
{ "type": "Feature", "properties": { "filename": "oregon_36_[-1,-1]_-118.52944724472306_42.13751723449763.png" }, "geometry": { "type": "Point", "coordinates": [ -118.529447244723059, 42.137517234497629 ] } },
{ "type": "Feature", "properties": { "filename": "oregon_36_[-1,0]_-118.51733134206391_42.13751723449763.png" }, "geometry": { "type": "Point", "coordinates": [ -118.517331342063912, 42.137517234497629 ] } },
{ "type": "Feature", "properties": { "filename": "oregon_36_[-1,1]_-118.50521543940476_42.13751723449763.png" }, "geometry": { "type": "Point", "coordinates": [ -118.505215439404765, 42.137517234497629 ] } },
{ "type": "Feature", "properties": { "filename": "oregon_36_[0,-1]_-118.52944724472306_42.14650034624754.png" }, "geometry": { "type": "Point", "coordinates": [ -118.529447244723059, 42.146500346247542 ] } },
{ "type": "Feature", "properties": { "filename": "oregon_36_[0,0]_-118.51733134206391_42.14650034624754.png" }, "geometry": { "type": "Point", "coordinates": [ -118.517331342063912, 42.146500346247542 ] } },
{ "type": "Feature", "properties": { "filename": "oregon_36_[0,1]_-118.50521543940476_42.14650034624754.png" }, "geometry": { "type": "Point", "coordinates": [ -118.505215439404765, 42.146500346247542 ] } },
{ "type": "Feature", "properties": { "filename": "oregon_36_[1,-1]_-118.52944724472306_42.155483457997455.png" }, "geometry": { "type": "Point", "coordinates": [ -118.529447244723059, 42.155483457997455 ] } },
{ "type": "Feature", "properties": { "filename": "oregon_36_[1,0]_-118.51733134206391_42.155483457997455.png" }, "geometry": { "type": "Point", "coordinates": [ -118.517331342063912, 42.155483457997455 ] } },
{ "type": "Feature", "properties": { "filename": "oregon_36_[1,1]_-118.50521543940476_42.155483457997455.png" }, "geometry": { "type": "Point", "coordinates": [ -118.505215439404765, 42.155483457997455 ] } }
]
}
